{
  "add": "Додати",
  "archive": "Архів",
  "arrow-down": "Стрілка вниз",
  "arrow-left": "Стрілка вліво",
  "arrow-left-down": "Стрілка вниз ліворуч",
  "arrow-left-up": "Стрілка вгору ліворуч",
  "arrow-right": "Стрілка вправо",
  "arrow-right-down": "Стрілка вниз праворуч",
  "arrow-right-up": "Стрілка вгору праворуч",
  "arrow-up": "Стрілка вгору",
  "attachment": "Вкладення",
  "backspace": "Клавіша Backspace",
  "ban": "Заборона",
  "bar-chart": "Стовпчикова діаграма",
  "bar-chart-alt": "Стовпчикова діаграма",
  "board": "Дошка",
  "bold": "Жирний шрифт",
  "book": "Книга",
  "bookmark": "Закладка",
  "calendar": "Календар",
  "call": "Дзвінок",
  "camera": "Камера",
  "caret-down": "Каретка вниз",
  "caret-left": "Каретка вліво",
  "caret-right": "Каретка вправо",
  "caret-up": "Каретка вгору",
  "check": "Галочка",
  "chevron-double-down": "Подвійний шеврон вниз",
  "chevron-double-left": "Подвійний шеврон вліво",
  "chevron-double-right": "Подвійний шеврон вправо",
  "chevron-double-up": "Подвійний шеврон вгору",
  "chevron-down": "Шеврон вниз",
  "chevron-left": "Шеврон ліворуч",
  "chevron-right": "Шеврон праворуч",
  "chevron-up": "Шеврон вгору",
  "circle": "Коло",
  "circle-add": "Коло з плюсом",
  "circle-arrow-down": "Коло (стрілка вниз)",
  "circle-arrow-left": "Коло (стрілка вліво)",
  "circle-arrow-right": "Коло (стрілка вправо)",
  "circle-arrow-up": "Коло (стрілка вгору)",
  "circle-check": "Коло (галочка)",
  "circle-error": "Помилка (кругла)",
  "circle-help": "Коло (допомога)",
  "circle-information": "Інформація в колі",
  "circle-remove": "Коло (видалити)",
  "circle-warning": "Коло (попередження)",
  "clipboard": "Буфер обміну",
  "clipboard-check": "Буфер обміну (галочка)",
  "clipboard-list": "Буфер обміну (список)",
  "clock": "Годинник",
  "close": "Закрити",
  "cloud": "Хмара",
  "cloud-download": "Хмарне завантаження",
  "cloud-upload": "Завантаження у хмару",
  "cloudy": "Хмарно",
  "comment": "Коментар",
  "compass": "Компас",
  "computer": "Комп'ютер",
  "copy": "Копіювати",
  "credit-card": "Кредитна картка",
  "database": "База даних",
  "delete": "Видалити",
  "delete-alt": "Видалити (альтернативна)",
  "document": "Документ",
  "document-add": "Документ (додати)",
  "document-check": "Документ з позначкою",
  "document-download": "Завантажити документ",
  "document-empty": "Документ empty",
  "document-remove": "Документ (прибрати)",
  "download": "Завантажити",
  "drag": "Перетягування",
  "drop": "Drop",
  "edit": "Редагувати",
  "edit-alt": "Редагувати (альт)",
  "email": "Пошта",
  "enter": "Enter",
  "expand": "Розгорнути",
  "export": "Експорт",
  "external-link": "Зовнішнє посилання",
  "eye": "Око",
  "eye-off": "Око (вимкнено)",
  "favorite": "Улюблене",
  "filter": "Фільтр",
  "filter-1": "Фільтр",
  "filter-alt": "Фільтр (альт)",
  "flag": "Прапор",
  "fog": "Туман",
  "folder": "Папка",
  "folder-add": "Додати папку",
  "folder-check": "Папка (галочка)",
  "folder-download": "Папка завантаження",
  "folder-remove": "Папка (видалити)",
  "grid": "Сітка",
  "heart": "Серце",
  "home": "Будинок",
  "image": "Зображення",
  "inbox": "Вхідні",
  "italic": "Курсив",
  "laptop": "Ноутбук",
  "layers": "Шари",
  "layout": "Макет",
  "link": "Посилання",
  "link-alt": "Посилання Alt",
  "list": "Список",
  "location": "Локація",
  "lock": "Замок",
  "log-in": "Вхід",
  "log-out": "Вихід",
  "map": "Карта",
  "megaphone": "Мегафон",
  "menu": "Меню",
  "message": "Повідомлення",
  "message-alt": "Повідомлення (альтернативне)",
  "minimize": "Згорнути",
  "mobile": "Мобільний",
  "moon": "Місяць",
  "next": "Далі",
  "notification": "Сповіщення",
  "notification-off": "Сповіщення (вимкнено)",
  "options-horizontal": "Параметри горизонтально",
  "options-vertical": "Вертикальні параметри",
  "pause": "Пауза",
  "pen": "Ручка",
  "percentage": "Відсоток",
  "pin": "Шпилька",
  "play": "Грати",
  "previous": "Попередній",
  "print": "Друк",
  "rain": "Дощ",
  "refresh": "Оновити",
  "remove": "Видалити",
  "reorder": "Змінити порядок",
  "reorder-alt": "Перевпорядкувати (альтернативно)",
  "repeat": "Повтор",
  "save": "Зберегти",
  "search": "Пошук",
  "select": "Вибрати",
  "send": "Відправити",
  "settings": "Налаштування",
  "share": "Поділ",
  "shopping-cart": "Візок для покупок",
  "shopping-cart-add": "Додати до візка",
  "shuffle": "Перемішати",
  "snow": "Сніг",
  "snowflake": "Сніжинка",
  "sort": "Сортування",
  "speakers": "Динаміки",
  "stop": "Зупинити",
  "storm": "Шторм",
  "strikethrough": "Закреслення",
  "sun": "Сонце",
  "sunrise": "Схід сонця",
  "sunrise-alt": "Світанок (альтернативна)",
  "sunset": "Захід сонця",
  "switch": "Перемикач",
  "table": "Стіл",
  "tablet": "Планшет",
  "tag": "Тег",
  "temperature": "Температура",
  "text": "Текст",
  "three-rows": "Три рядки",
  "two-columns": "Дві колонки",
  "two-rows": "Два рядки",
  "underline": "Підкреслення",
  "undo": "Скасувати",
  "unlock": "Розблокувати",
  "user": "Користувач",
  "user-add": "Додати користувача",
  "user-check": "Перевірка користувача",
  "user-remove": "Користувач (видалити)",
  "users": "Користувачі",
  "volume-off": "Гучність (вимкнено)",
  "volume-up": "Збільшити гучність",
  "warning": "Попередження",
  "webcam": "Вебкамера",
  "wind": "Вітер",
  "window": "Вікно",
  "zoom-in": "Збільшення",
  "zoom-out": "Зменшити"
}
