{
  "account-login": {
    "name": "Вхід",
    "mediaKey": "c0f1e1a9-459e-405c-bb5b-d67fe39a5040",
    "keys": [
      "авторизація",
      "ака",
      "акаунт",
      "аккаунт",
      "вхід",
      "вхід до системи",
      "вхід у профіль",
      "кабінет",
      "логін",
      "логін користувача",
      "обліковий запис",
      "профіль",
      "account",
      "login",
      "profile",
      "sign in",
      "user"
    ]
  },
  "account-logout": {
    "name": "Вихід з облікового запису",
    "mediaKey": "4903fc76-b81d-4396-90c4-cf20a5a73d3d",
    "keys": [
      "ака",
      "акаунт",
      "аккаунт",
      "вийти з акаунта",
      "вийти з системи",
      "вихід з облікового запису",
      "вихід із акаунта",
      "завершення сеансу",
      "кабінет",
      "обліковий запис",
      "профіль",
      "account",
      "login",
      "logout",
      "logout кнопка",
      "profile",
      "sign out",
      "user"
    ]
  },
  "action-redo": {
    "name": "Повторити дію",
    "mediaKey": "c749a624-a717-467e-81b4-0ff00499657d",
    "keys": [
      "вернути",
      "дія",
      "екшен",
      "зробити знову",
      "клік",
      "операція",
      "повторити",
      "повторна дія",
      "подія",
      "action",
      "activity",
      "execute",
      "forward undo",
      "interaction",
      "reapply",
      "redo",
      "repeat",
      "trigger"
    ]
  },
  "action-undo": {
    "name": "Скасувати дію",
    "mediaKey": "6d9f1671-9f27-467c-8a02-e534cf7f8751",
    "keys": [
      "дія",
      "екшен",
      "клік",
      "операція",
      "повернути",
      "подія",
      "скасувати",
      "action",
      "activity",
      "back",
      "ctrl z",
      "execute",
      "interaction",
      "reverse",
      "revert",
      "rollback",
      "step back",
      "trigger",
      "undo"
    ]
  },
  "align-center": {
    "name": "Вирівняти по центру",
    "mediaKey": "1f39ba83-f8df-4265-9bb0-6f97b4d899f4",
    "keys": [
      "аліґн",
      "вирівнювання",
      "вирівняти",
      "кентер",
      "по центру",
      "центр",
      "центрування",
      "align",
      "alignment",
      "center",
      "center align",
      "layout",
      "middle"
    ]
  },
  "align-left": {
    "name": "Вирівняти ліворуч",
    "mediaKey": "2f678fdd-3843-4969-b91e-d26c3caafcaa",
    "keys": [
      "←",
      "аліґн",
      "вирівнювання",
      "вирівняти",
      "зліва",
      "лефт",
      "ліва сторона",
      "лівий бік",
      "лівий напрямок",
      "по центру",
      "align",
      "alignment",
      "arrow left",
      "layout",
      "left",
      "left arrow",
      "west"
    ]
  },
  "align-right": {
    "name": "Вирівняти праворуч",
    "mediaKey": "3ef6fd51-4a9a-493f-8a9b-f87d6f647460",
    "keys": [
      "аліґн",
      "вирівнювання",
      "вирівняти",
      "по центру",
      "правильно",
      "праворуч",
      "ріґхт",
      "align",
      "alignment",
      "correct",
      "layout",
      "right",
      "right arrow"
    ]
  },
  "aperture": {
    "name": "Діафрагма",
    "mediaKey": "385d9406-b9a2-4986-b556-0f51bb0a3c75",
    "keys": [
      "апертуре",
      "діафрагма",
      "камера",
      "отвор діафрагми",
      "aperture",
      "aperture science",
      "f-stop"
    ]
  },
  "arrow-bottom": {
    "name": "Стрілка вниз",
    "mediaKey": "210e86fd-4601-4b7f-916a-5223d25a1afe",
    "keys": [
      "арров",
      "боттом",
      "вказівник",
      "дно",
      "напрямок",
      "низ",
      "стрілка",
      "стрілка напрям",
      "arrow",
      "arrow icon",
      "bottom",
      "bottom area",
      "footer"
    ]
  },
  "arrow-circle-bottom": {
    "name": "Стрілка вниз (коло)",
    "mediaKey": "9e6646ff-15a3-4432-a5b3-778fa75370f7",
    "keys": [
      "арров",
      "боттом",
      "вказівник",
      "дно",
      "кіркле",
      "коло",
      "напрямок",
      "низ",
      "окружність",
      "стрілка",
      "стрілка напрям",
      "arrow",
      "arrow icon",
      "bottom",
      "bottom area",
      "circle",
      "circle shape",
      "footer",
      "round"
    ]
  },
  "arrow-circle-left": {
    "name": "Стрілка в колі вліво",
    "mediaKey": "eeb90b8e-2cf8-4b23-97f3-f7b8b22a387d",
    "keys": [
      "←",
      "арров",
      "вказівник",
      "зліва",
      "кіркле",
      "коло",
      "лефт",
      "ліва сторона",
      "лівий бік",
      "лівий напрямок",
      "напрямок",
      "окружність",
      "стрілка",
      "стрілка напрям",
      "arrow",
      "arrow icon",
      "arrow left",
      "circle",
      "circle shape",
      "left",
      "left arrow",
      "round",
      "west"
    ]
  },
  "arrow-circle-right": {
    "name": "Стрілка в колі вправо",
    "mediaKey": "0159acfa-165e-460d-a595-4952b3a5d5ae",
    "keys": [
      "арров",
      "вказівник",
      "кіркле",
      "коло",
      "напрямок",
      "окружність",
      "правильно",
      "праворуч",
      "ріґхт",
      "стрілка",
      "стрілка напрям",
      "arrow",
      "arrow icon",
      "circle",
      "circle shape",
      "correct",
      "right",
      "right arrow",
      "round"
    ]
  },
  "arrow-circle-top": {
    "name": "Стрілка вгору (коло)",
    "mediaKey": "5e462b4b-a6f3-430b-a8cd-c491ef323c7a",
    "keys": [
      "арров",
      "верх",
      "верхівка",
      "вказівник",
      "зверху",
      "кіркле",
      "коло",
      "лідер",
      "напрямок",
      "окружність",
      "стрілка",
      "стрілка напрям",
      "топ",
      "arrow",
      "arrow icon",
      "circle",
      "circle shape",
      "max",
      "round",
      "top",
      "top list"
    ]
  },
  "arrow-left": {
    "name": "Стрілка вліво",
    "mediaKey": "25665035-0957-46c9-a1ba-5e26811ce308",
    "keys": [
      "←",
      "арров",
      "вказівник",
      "зліва",
      "лефт",
      "ліва сторона",
      "лівий бік",
      "лівий напрямок",
      "напрямок",
      "стрілка",
      "стрілка напрям",
      "arrow",
      "arrow icon",
      "arrow left",
      "left",
      "left arrow",
      "west"
    ]
  },
  "arrow-right": {
    "name": "Стрілка вправо",
    "mediaKey": "dd50b414-f492-422d-a9ab-66f5e3cc7e97",
    "keys": [
      "арров",
      "вказівник",
      "напрямок",
      "правильно",
      "праворуч",
      "ріґхт",
      "стрілка",
      "стрілка напрям",
      "arrow",
      "arrow icon",
      "correct",
      "right",
      "right arrow"
    ]
  },
  "arrow-thick-bottom": {
    "name": "Стрілка вниз (товста)",
    "mediaKey": "04928d34-1b70-498a-abcf-2f03a596df06",
    "keys": [
      "арров",
      "боттом",
      "вказівник",
      "густий",
      "дно",
      "напрямок",
      "низ",
      "стрілка",
      "стрілка напрям",
      "товстий",
      "щільний",
      "arrow",
      "arrow icon",
      "bold",
      "bottom",
      "bottom area",
      "fat",
      "footer",
      "heavy",
      "strong",
      "thick",
      "wide"
    ]
  },
  "arrow-thick-left": {
    "name": "Стрілка вліво (товста)",
    "mediaKey": "6a14e8b5-04b7-4d3b-b11d-6226a4f71cdb",
    "keys": [
      "←",
      "арров",
      "вказівник",
      "густий",
      "зліва",
      "лефт",
      "ліва сторона",
      "лівий бік",
      "лівий напрямок",
      "напрямок",
      "стрілка",
      "стрілка напрям",
      "товстий",
      "щільний",
      "arrow",
      "arrow icon",
      "arrow left",
      "bold",
      "fat",
      "heavy",
      "left",
      "left arrow",
      "strong",
      "thick",
      "west",
      "wide"
    ]
  },
  "arrow-thick-right": {
    "name": "Стрілка вправо (товста)",
    "mediaKey": "84fee8b9-426c-4ecc-925e-90c34bb5350c",
    "keys": [
      "арров",
      "вказівник",
      "густий",
      "напрямок",
      "правильно",
      "праворуч",
      "ріґхт",
      "стрілка",
      "стрілка напрям",
      "товстий",
      "щільний",
      "arrow",
      "arrow icon",
      "bold",
      "correct",
      "fat",
      "heavy",
      "right",
      "right arrow",
      "strong",
      "thick",
      "wide"
    ]
  },
  "arrow-thick-top": {
    "name": "Стрілка вгору (товста)",
    "mediaKey": "e4c115a2-fc44-4e74-a74b-fa8ea81ad13f",
    "keys": [
      "арров",
      "верх",
      "верхівка",
      "вказівник",
      "густий",
      "зверху",
      "лідер",
      "напрямок",
      "стрілка",
      "стрілка напрям",
      "товстий",
      "топ",
      "щільний",
      "arrow",
      "arrow icon",
      "bold",
      "fat",
      "heavy",
      "max",
      "strong",
      "thick",
      "top",
      "top list",
      "wide"
    ]
  },
  "arrow-top": {
    "name": "Стрілка вгору",
    "mediaKey": "caa1663d-2150-4751-aa7c-4153b09e393b",
    "keys": [
      "арров",
      "верх",
      "верхівка",
      "вказівник",
      "зверху",
      "лідер",
      "напрямок",
      "стрілка",
      "стрілка напрям",
      "топ",
      "arrow",
      "arrow icon",
      "max",
      "top",
      "top list"
    ]
  },
  "audio": {
    "name": "Аудіо",
    "mediaKey": "a7735d53-fc90-4662-8e18-3e0808ebb85f",
    "keys": [
      "аудіо",
      "аудіо доріжка",
      "звук",
      "audio",
      "podcast",
      "soundwave"
    ]
  },
  "audio-spectrum": {
    "name": "Аудіоспектр",
    "mediaKey": "1bfdebd3-128c-4db8-91b7-f9ad31b99a78",
    "keys": [
      "аудіо",
      "аудіо доріжка",
      "діапазон",
      "звук",
      "кольори",
      "спектр",
      "audio",
      "band",
      "color",
      "frequencies",
      "light",
      "podcast",
      "range",
      "soundwave",
      "spectrum"
    ]
  },
  "badge": {
    "name": "Значок",
    "mediaKey": "115fe582-c451-423f-8cce-b347bac2a77b",
    "keys": [
      "бадґе",
      "бейдж",
      "знагорода",
      "значок",
      "значок профілю",
      "badge",
      "badge icon"
    ]
  },
  "ban": {
    "name": "Заборона",
    "mediaKey": "c3328537-4b1b-4cf4-9dc0-c7cae6b8da16",
    "keys": [
      "бан",
      "заблокувати",
      "заборона",
      "ban",
      "ban hammer",
      "block user"
    ]
  },
  "bar-chart": {
    "name": "Стовпчикова діаграма",
    "mediaKey": "41c25bce-0b43-46e2-a294-ba20ab21a075",
    "keys": [
      "бар",
      "графік",
      "діаграма",
      "стояк",
      "чарт",
      "bar",
      "chart",
      "chart icon",
      "progress bar",
      "pub",
      "stats"
    ]
  },
  "basket": {
    "name": "Кошик",
    "mediaKey": "de0742e8-6b39-4b52-8bba-e61ad8d134ad",
    "keys": [
      "баскет",
      "кошик",
      "плетений кошик",
      "basket",
      "basket icon",
      "shopping basket"
    ]
  },
  "battery-empty": {
    "name": "Розряджена батарея",
    "mediaKey": "71881b61-0df0-481e-be11-091c41111adf",
    "keys": [
      "🔋",
      "акумулятор",
      "баттерй",
      "емптй",
      "заряд батареї",
      "немає даних",
      "нічого",
      "порожнеча",
      "порожнє поле",
      "порожній",
      "battery",
      "battery level",
      "empty",
      "empty box",
      "empty box state",
      "empty list",
      "empty placeholder",
      "empty state",
      "no data",
      "nothing inside",
      "power cell",
      "void",
      "zero items"
    ]
  },
  "battery-full": {
    "name": "Акумулятор (повний)",
    "mediaKey": "fdd57012-f788-4eed-b143-97440a33a489",
    "keys": [
      "🔋",
      "акумулятор",
      "баттерй",
      "заряд батареї",
      "наповнений",
      "повний",
      "повністю",
      "фулл",
      "battery",
      "battery level",
      "full",
      "full capacity",
      "full icon",
      "power cell"
    ]
  },
  "beaker": {
    "name": "Колба",
    "mediaKey": "50cabc5d-3bd4-4112-b0b8-59c65e371096",
    "keys": [
      "колба",
      "лабораторія",
      "мензурка",
      "пробірка",
      "склянка",
      "хімія",
      "beaker",
      "flask",
      "lab"
    ]
  },
  "bell": {
    "name": "Дзвінок",
    "mediaKey": "298adba4-01db-4703-b437-96cacddb2623",
    "keys": [
      "🔔",
      "белл",
      "дзвінок",
      "дзвіночок",
      "дзвоник",
      "alarm bell",
      "bell",
      "notif bell"
    ]
  },
  "bluetooth": {
    "name": "Bluetooth",
    "mediaKey": "6715c0bd-ac0b-412b-9799-7de56a6cf5ad",
    "keys": [
      "2.4 ghz",
      "безпровідне з'єднання",
      "блуетоот",
      "bluetooth",
      "bluetooth logo",
      "bt"
    ]
  },
  "bold": {
    "name": "Жирний шрифт",
    "mediaKey": "fa586b78-9321-47de-ad52-4ac5ca22c3ae",
    "keys": [
      "болд",
      "виділити",
      "жирний",
      "жирний текст",
      "bold",
      "bold font",
      "strong тег"
    ]
  },
  "bolt": {
    "name": "Блискавка",
    "mediaKey": "64f301b3-43fc-4437-9afd-61e58ea96a1c",
    "keys": [
      "блискавка",
      "болт",
      "болт гвинт",
      "швидкісний",
      "bolt",
      "lightning"
    ]
  },
  "book": {
    "name": "Книга",
    "mediaKey": "a9ee073a-61de-4459-98f2-cd31829a85d5",
    "keys": [
      "📚",
      "боок",
      "книга",
      "читати",
      "book",
      "book icon",
      "hardcover"
    ]
  },
  "bookmark": {
    "name": "Закладка",
    "mediaKey": "18012b3b-9c67-4e3b-b90f-bf608b06568f",
    "keys": [
      "🔖",
      "боокмарк",
      "закладка",
      "стрічка",
      "bookmark",
      "bookmark icon",
      "save"
    ]
  },
  "box": {
    "name": "Коробка",
    "mediaKey": "1d9f36c5-daac-4b10-b77a-2abdad8774b1",
    "keys": [
      "бокс",
      "коробка",
      "пакунок",
      "ящик",
      "box",
      "box parcel"
    ]
  },
  "briefcase": {
    "name": "Портфель",
    "mediaKey": "b7e9afdc-ac95-48bd-97f3-33311ce0b4a4",
    "keys": [
      "бріефкасе",
      "валіза для документів",
      "портфель",
      "attaché",
      "briefcase",
      "business case"
    ]
  },
  "british-pound": {
    "name": "Фунт стерлінгів",
    "mediaKey": "e09da2c9-121b-4cf9-a0ea-fb00a318dae4",
    "keys": [
      "£",
      "англія",
      "британія",
      "британський",
      "поунд",
      "прапор англії",
      "фунт",
      "british",
      "great britain",
      "london",
      "pound",
      "pound sterling",
      "uk",
      "union jack"
    ]
  },
  "browser": {
    "name": "Браузер",
    "mediaKey": "a2c7be3a-d507-440a-b655-2c9c2c7e58d2",
    "keys": [
      "браузер",
      "бровсер",
      "оглядач",
      "browser",
      "chrome",
      "web browser"
    ]
  },
  "brush": {
    "name": "Пензлик",
    "mediaKey": "43560729-fa18-4202-aa11-0d7044fdae80",
    "keys": [
      "бруш",
      "пензлик",
      "фарбувати",
      "щітка",
      "brush",
      "brush tool"
    ]
  },
  "bug": {
    "name": "Жук",
    "mediaKey": "fc3d4f81-f9dd-417d-9345-343b2ab8ea56",
    "keys": [
      "баг",
      "буґ",
      "жук",
      "помилка",
      "bug",
      "issue",
      "software bug"
    ]
  },
  "bullhorn": {
    "name": "Гучномовець",
    "mediaKey": "3d54c006-5661-4a1d-9d57-370b9012f2c0",
    "keys": [
      "гучний звук",
      "гучномовець",
      "мегафон",
      "оголошення",
      "сповіщення",
      "bullhorn",
      "callout",
      "megaphone",
      "speaker"
    ]
  },
  "calculator": {
    "name": "Калькулятор",
    "mediaKey": "89715333-9ad7-4de7-bb9a-b2d82f7391de",
    "keys": [
      "калкулатор",
      "калькулятор",
      "рахувати",
      "calc",
      "calculator",
      "math keypad"
    ]
  },
  "calendar": {
    "name": "Календар",
    "mediaKey": "ee1d6d05-aff0-4e4f-91da-6ec5b4a01184",
    "keys": [
      "📅",
      "дата",
      "календар",
      "calendar",
      "planner",
      "schedule"
    ]
  },
  "camera-slr": {
    "name": "Камера SLR",
    "mediaKey": "5e9800c2-7339-4759-87e9-e15ff8fa4664",
    "keys": [
      "📷",
      "альта",
      "блокчейн",
      "валюта",
      "камера",
      "коін",
      "крипта",
      "криптовалюта",
      "монета",
      "токен",
      "фотоапарат",
      "blockchain",
      "camera",
      "camera icon",
      "coin",
      "crypto",
      "cryptocurrency",
      "photo",
      "slr",
      "token"
    ]
  },
  "caret-bottom": {
    "name": "Каретка вниз",
    "mediaKey": "65ef71f3-0e31-4cd0-a20e-f994c04a2d77",
    "keys": [
      "боттом",
      "вставка",
      "вставний маркер",
      "дно",
      "карет",
      "курсор",
      "низ",
      "bottom",
      "bottom area",
      "caret",
      "caret icon",
      "footer"
    ]
  },
  "caret-left": {
    "name": "Каретка вліво",
    "mediaKey": "723ee5fa-efe1-429c-86b1-52691fccf158",
    "keys": [
      "←",
      "вставка",
      "вставний маркер",
      "зліва",
      "карет",
      "курсор",
      "лефт",
      "ліва сторона",
      "лівий бік",
      "лівий напрямок",
      "arrow left",
      "caret",
      "caret icon",
      "left",
      "left arrow",
      "west"
    ]
  },
  "caret-right": {
    "name": "Каретка вправо",
    "mediaKey": "9677d5db-6d49-460b-a600-ab961edb6142",
    "keys": [
      "вставка",
      "вставний маркер",
      "карет",
      "курсор",
      "правильно",
      "праворуч",
      "ріґхт",
      "caret",
      "caret icon",
      "correct",
      "right",
      "right arrow"
    ]
  },
  "caret-top": {
    "name": "Каретка вгору",
    "mediaKey": "1d2233e8-f72a-4b90-9299-3c49e7b33edb",
    "keys": [
      "верх",
      "верхівка",
      "вставка",
      "вставний маркер",
      "зверху",
      "карет",
      "курсор",
      "лідер",
      "топ",
      "caret",
      "caret icon",
      "max",
      "top",
      "top list"
    ]
  },
  "cart": {
    "name": "Кошик",
    "mediaKey": "fbdc1245-cfc3-4187-974a-c6c6866a89eb",
    "keys": [
      "🛒",
      "візок",
      "карт",
      "корзина",
      "кошик",
      "cart",
      "cart icon",
      "shopping cart"
    ]
  },
  "chat": {
    "name": "Чат",
    "mediaKey": "222234f0-089b-4608-8025-b6d68ac33daa",
    "keys": [
      "діалог",
      "месенджер",
      "переписка",
      "повідомлення",
      "розмова",
      "спілкування",
      "чат",
      "чатик",
      "chat",
      "conversation",
      "message",
      "messaging",
      "messenger",
      "talk"
    ]
  },
  "check": {
    "name": "Галочка",
    "mediaKey": "0d5910a8-bc0a-49a2-b708-abac18792928",
    "keys": [
      "галочка",
      "перевірити",
      "чекк",
      "check",
      "check mark",
      "done"
    ]
  },
  "chevron-bottom": {
    "name": "Шеврон вниз",
    "mediaKey": "9791a3f3-21c0-431d-a82b-9c41e8c57b0e",
    "keys": [
      "боттом",
      "вказівник",
      "галон",
      "дно",
      "низ",
      "стрілка v",
      "чеврон",
      "шеврон",
      "bottom",
      "bottom area",
      "chevron",
      "footer"
    ]
  },
  "chevron-left": {
    "name": "Шеврон ліворуч",
    "mediaKey": "c0343d4e-237e-449d-b794-535eb01c21cd",
    "keys": [
      "←",
      "вказівник",
      "галон",
      "зліва",
      "лефт",
      "ліва сторона",
      "лівий бік",
      "лівий напрямок",
      "стрілка v",
      "чеврон",
      "шеврон",
      "arrow left",
      "chevron",
      "left",
      "left arrow",
      "west"
    ]
  },
  "chevron-right": {
    "name": "Шеврон праворуч",
    "mediaKey": "ca033336-f553-4fb8-becb-e2a4879f219a",
    "keys": [
      "вказівник",
      "галон",
      "правильно",
      "праворуч",
      "ріґхт",
      "стрілка v",
      "чеврон",
      "шеврон",
      "chevron",
      "correct",
      "right",
      "right arrow"
    ]
  },
  "chevron-top": {
    "name": "Шеврон вгору",
    "mediaKey": "411b4b8b-246c-45a5-a620-d4412bbfa0da",
    "keys": [
      "верх",
      "верхівка",
      "вказівник",
      "галон",
      "зверху",
      "лідер",
      "стрілка v",
      "топ",
      "чеврон",
      "шеврон",
      "chevron",
      "max",
      "top",
      "top list"
    ]
  },
  "circle-check": {
    "name": "Коло (галочка)",
    "mediaKey": "b59a87b8-f94e-4e0b-bb25-5d81db258122",
    "keys": [
      "галочка",
      "кіркле",
      "коло",
      "окружність",
      "перевірити",
      "чекк",
      "check",
      "check mark",
      "circle",
      "circle shape",
      "done",
      "round"
    ]
  },
  "circle-x": {
    "name": "Коло (хрестик)",
    "mediaKey": "7bb33d5c-0a91-4a42-9a0d-3bc0fd884250",
    "keys": [
      "ікс",
      "кіркле",
      "коло",
      "крестик",
      "літера x",
      "невідоме",
      "окружність",
      "перехрестя",
      "circle",
      "circle shape",
      "letter x",
      "round",
      "x",
      "X",
      "x shape"
    ]
  },
  "clipboard": {
    "name": "Буфер обміну",
    "mediaKey": "7ee7b02c-624f-4fd6-ab6d-4500648779bd",
    "keys": [
      "буфер обміну",
      "кліпбоард",
      "список",
      "clipboard",
      "clipboard icon",
      "copy"
    ]
  },
  "clock": {
    "name": "Годинник",
    "mediaKey": "bbace819-8267-48e7-83dc-eb87fd75f02a",
    "keys": [
      "🕒",
      "годинник",
      "клокк",
      "analog clock",
      "clock",
      "time",
      "watch"
    ]
  },
  "cloud": {
    "name": "Хмара",
    "mediaKey": "22d4629c-ce49-41e1-b9a1-6b80a86d5776",
    "keys": [
      "☁️",
      "клоуд",
      "хмара",
      "cloud",
      "cloud icon",
      "cloud storage",
      "sky"
    ]
  },
  "cloud-download": {
    "name": "Хмарне завантаження",
    "mediaKey": "892293d3-a9c4-472b-9edb-ed7cac8f5032",
    "keys": [
      "☁️",
      "довнлоад",
      "завантаження",
      "завантажити",
      "завантажити файл",
      "клоуд",
      "хмара",
      "cloud",
      "cloud download",
      "cloud icon",
      "cloud storage",
      "download",
      "download arrow",
      "download button",
      "download data",
      "download file",
      "download icon",
      "file download",
      "import file",
      "save arrow",
      "save file",
      "save offline",
      "sky"
    ]
  },
  "cloud-upload": {
    "name": "Завантаження у хмару",
    "mediaKey": "6832ec20-9aad-48b1-8655-3d250fb6bdbd",
    "keys": [
      "☁️",
      "аплоад",
      "відправити файл",
      "завантаження",
      "завантажити",
      "залити",
      "клоуд",
      "хмара",
      "cloud",
      "cloud icon",
      "cloud storage",
      "send file",
      "sky",
      "upload"
    ]
  },
  "cloudy": {
    "name": "Хмарно",
    "mediaKey": "aedfe5d8-7b9d-425d-97c1-c1d12c064a19",
    "keys": [
      "пасмурно",
      "похмуро",
      "хмарно",
      "clouds",
      "cloudy",
      "gray sky",
      "overcast",
      "weather"
    ]
  },
  "code": {
    "name": "Код",
    "mediaKey": "98540dde-72b4-4adc-8b43-86211c00cc52",
    "keys": [
      "<>",
      "код",
      "коде",
      "програмування",
      "code",
      "source"
    ]
  },
  "cog": {
    "name": "Шестерня",
    "mediaKey": "ec980127-d5d1-412e-a635-a326522987fc",
    "keys": [
      "гвинтик",
      "зубчасте колесо",
      "коґ",
      "шестерня",
      "шестірня",
      "cog",
      "cogwheel",
      "gear",
      "settings"
    ]
  },
  "collapse-down": {
    "name": "Collapse вниз",
    "mediaKey": "5d51beec-3b6c-4fd7-a8f0-c99749fe5e35",
    "keys": [
      "вниз",
      "довн",
      "згорнути",
      "згортання",
      "зменшити",
      "колапс",
      "коллапсе",
      "опустити",
      "рух донизу",
      "стрілка вниз",
      "accordion",
      "arrow downwards",
      "collapse",
      "collapse panel",
      "descending arrow",
      "down",
      "down arrow",
      "down direction",
      "down icon",
      "down swipe",
      "download arrow",
      "downward",
      "move down",
      "scroll down"
    ]
  },
  "collapse-left": {
    "name": "Collapse ліворуч",
    "mediaKey": "c21c3f67-bc2e-4165-8786-1955dc7a2aa3",
    "keys": [
      "←",
      "згорнути",
      "згортання",
      "зліва",
      "зменшити",
      "колапс",
      "коллапсе",
      "лефт",
      "ліва сторона",
      "лівий бік",
      "лівий напрямок",
      "accordion",
      "arrow left",
      "collapse",
      "collapse panel",
      "left",
      "left arrow",
      "west"
    ]
  },
  "collapse-right": {
    "name": "Collapse праворуч",
    "mediaKey": "3a0e1080-5dd3-4752-80c3-8172f8e19d79",
    "keys": [
      "згорнути",
      "згортання",
      "зменшити",
      "колапс",
      "коллапсе",
      "правильно",
      "праворуч",
      "ріґхт",
      "accordion",
      "collapse",
      "collapse panel",
      "correct",
      "right",
      "right arrow"
    ]
  },
  "collapse-up": {
    "name": "Collapse вгору",
    "mediaKey": "4a4117a6-7376-4205-8e2a-e30fca45c05f",
    "keys": [
      "ап",
      "вгору",
      "верх",
      "згорнути",
      "згортання",
      "зменшити",
      "колапс",
      "коллапсе",
      "підняти",
      "accordion",
      "arrow up",
      "boost",
      "collapse",
      "collapse panel",
      "up"
    ]
  },
  "command": {
    "name": "Клавіша команди",
    "mediaKey": "465fcc8a-6b21-4757-a2ab-48fd8df5b806",
    "keys": [
      "команда",
      "комманд",
      "наказ",
      "cmd",
      "command",
      "command key"
    ]
  },
  "comment-square": {
    "name": "Коментар (квадрат)",
    "mediaKey": "67748fb5-8587-4242-b51d-97018670891e",
    "keys": [
      "відгук",
      "відповідь",
      "додати коментар",
      "замітка",
      "касовий термінал",
      "квад",
      "квадрат",
      "комент",
      "коментар",
      "платіжна система Square",
      "плитка",
      "площа",
      "площі",
      "репліка",
      "фігура 4x4",
      "comment",
      "discussion",
      "feedback",
      "message",
      "reply",
      "square",
      "Square",
      "Squareup",
      "talk",
      "thread"
    ]
  },
  "compass": {
    "name": "Компас",
    "mediaKey": "ae899cdd-c069-44b3-97db-6eb7fc2e37a0",
    "keys": [
      "компас",
      "компасс",
      "навігація",
      "орієнтир",
      "compass",
      "north"
    ]
  },
  "contrast": {
    "name": "Контраст",
    "mediaKey": "54fba3c0-b621-4284-ae2a-9382764352d5",
    "keys": [
      "відмінність",
      "контраст",
      "темний/світлий",
      "contrast",
      "contrast slider"
    ]
  },
  "copywriting": {
    "name": "Копірайтинг",
    "mediaKey": "1adfb0a1-4f35-48e0-b0a1-d12eeae1fa66",
    "keys": [
      "бренд",
      "контент",
      "копірайтинг",
      "логотип",
      "реклама",
      "тексти",
      "copywriting"
    ]
  },
  "credit-card": {
    "name": "Кредитна картка",
    "mediaKey": "eb939d7d-bd48-4d5c-83ed-0e15051d70a9",
    "keys": [
      "банківська картка",
      "візитка",
      "кард",
      "картка",
      "картку",
      "кредит",
      "кредіт",
      "пластикова картка",
      "bank card",
      "borrow",
      "card",
      "card ui",
      "credit",
      "credit card",
      "credit score"
    ]
  },
  "crop": {
    "name": "Кадрування",
    "mediaKey": "44ab2e01-42e2-4ca0-882e-f7e5f2356e3a",
    "keys": [
      "кадрування",
      "кроп",
      "обрізати",
      "обрізка фото",
      "урожай",
      "crop",
      "crop tool",
      "trim image"
    ]
  },
  "dashboard": {
    "name": "Панель керування",
    "mediaKey": "f63db468-5f26-47b9-afa2-fd92554abba7",
    "keys": [
      "дашбоард",
      "дашборд",
      "панель",
      "панель керування",
      "приладова",
      "приладова панель",
      "analytics board",
      "dashboard",
      "dashboard ui"
    ]
  },
  "data-transfer-download": {
    "name": "Передача даних (завантаження)",
    "mediaKey": "32f74896-2daf-4d04-b0ce-fab74dab141a",
    "keys": [
      "даних",
      "дані",
      "дата",
      "довнлоад",
      "завантаження",
      "завантажити",
      "завантажити файл",
      "інформація",
      "передача",
      "переказ",
      "перенос",
      "трансфер",
      "cloud download",
      "data",
      "data points",
      "dataset",
      "download",
      "download arrow",
      "download button",
      "download data",
      "download file",
      "download icon",
      "file download",
      "import file",
      "move",
      "save arrow",
      "save file",
      "save offline",
      "send",
      "transfer"
    ]
  },
  "data-transfer-upload": {
    "name": "Передача даних (вивантаження)",
    "mediaKey": "5c5fb3cf-091c-4a66-ab6d-426c0c03ce6c",
    "keys": [
      "аплоад",
      "відправити файл",
      "даних",
      "дані",
      "дата",
      "завантаження",
      "завантажити",
      "залити",
      "інформація",
      "передача",
      "переказ",
      "перенос",
      "трансфер",
      "data",
      "data points",
      "dataset",
      "move",
      "send",
      "send file",
      "transfer",
      "upload"
    ]
  },
  "delete": {
    "name": "Видалити",
    "mediaKey": "deed2888-8b81-47b0-88a9-cab3623ceee2",
    "keys": [
      "видалити",
      "делете",
      "delete",
      "delete icon",
      "remove",
      "trash"
    ]
  },
  "dial": {
    "name": "Циферблат",
    "mediaKey": "aa2e0d99-749b-4218-812c-4555c493c002",
    "keys": [
      "крутилка",
      "набір",
      "обертати",
      "регулятор",
      "ручка",
      "циферблат",
      "dial",
      "dialer"
    ]
  },
  "document": {
    "name": "Документ",
    "mediaKey": "eece95cf-a36b-4d54-86db-d3ff45601021",
    "keys": [
      "док",
      "документ",
      "документація",
      "звіт",
      "файл",
      "document",
      "paper",
      "pdf"
    ]
  },
  "dollar": {
    "name": "Долар",
    "mediaKey": "6d3ef2a0-25ae-4167-bd02-7c3fdf912a41",
    "keys": [
      "американський долар",
      "валюта",
      "долар",
      "доллар",
      "зелена валюта",
      "bucks",
      "currency",
      "dollar",
      "dollar bill",
      "dollar cash",
      "dollar icon",
      "dollar money",
      "dollar sign",
      "greenback",
      "usd",
      "usd currency"
    ]
  },
  "double-quote-sans-left": {
    "name": "Лапки подвійні ліві",
    "mediaKey": "53f1fe62-3584-4273-8815-84e49d0c4e94",
    "keys": [
      "\"\"",
      "←",
      "без засічок",
      "двійний режим",
      "двічі",
      "двічі більше",
      "доубле",
      "зліва",
      "квоте",
      "лефт",
      "ліва сторона",
      "лівий бік",
      "лівий напрямок",
      "подвійний",
      "подвоєння",
      "подвоїти",
      "цитата",
      "arrow left",
      "clean font",
      "double",
      "double arrow",
      "double dose",
      "double icon",
      "double line",
      "double size",
      "double tap",
      "duplicate",
      "grotesk",
      "left",
      "left arrow",
      "modern font",
      "quotation",
      "quote",
      "sans",
      "sans-serif",
      "text",
      "typeface",
      "typography",
      "west"
    ]
  },
  "double-quote-sans-right": {
    "name": "Лапки подвійні праві",
    "mediaKey": "c2c79c53-9c6b-402e-ac9a-9b33300632a0",
    "keys": [
      "\"\"",
      "без засічок",
      "двійний режим",
      "двічі",
      "двічі більше",
      "доубле",
      "квоте",
      "подвійний",
      "подвоєння",
      "подвоїти",
      "правильно",
      "праворуч",
      "ріґхт",
      "цитата",
      "clean font",
      "correct",
      "double",
      "double arrow",
      "double dose",
      "double icon",
      "double line",
      "double size",
      "double tap",
      "duplicate",
      "grotesk",
      "modern font",
      "quotation",
      "quote",
      "right",
      "right arrow",
      "sans",
      "sans-serif",
      "text",
      "typeface",
      "typography"
    ]
  },
  "double-quote-serif-left": {
    "name": "Подвійні лапки (із засічками) ліворуч",
    "mediaKey": "2e42d07b-f9c5-44e1-8a09-3352efde0702",
    "keys": [
      "\"\"",
      "←",
      "антиква",
      "гарнітура",
      "двійний режим",
      "двічі",
      "двічі більше",
      "доубле",
      "засічковий",
      "зліва",
      "квоте",
      "лефт",
      "ліва сторона",
      "лівий бік",
      "лівий напрямок",
      "подвійний",
      "подвоєння",
      "подвоїти",
      "серіф",
      "цитата",
      "шрифт з зарубками",
      "arrow left",
      "classic font",
      "double",
      "double arrow",
      "double dose",
      "double icon",
      "double line",
      "double size",
      "double tap",
      "duplicate",
      "font family",
      "left",
      "left arrow",
      "quotation",
      "quote",
      "serif",
      "serif font",
      "times",
      "typography",
      "west"
    ]
  },
  "double-quote-serif-right": {
    "name": "Подвійні лапки (із засічками) праворуч",
    "mediaKey": "32f2054b-73b9-4763-970c-99d61507279b",
    "keys": [
      "\"\"",
      "антиква",
      "гарнітура",
      "двійний режим",
      "двічі",
      "двічі більше",
      "доубле",
      "засічковий",
      "квоте",
      "подвійний",
      "подвоєння",
      "подвоїти",
      "правильно",
      "праворуч",
      "ріґхт",
      "серіф",
      "цитата",
      "шрифт з зарубками",
      "classic font",
      "correct",
      "double",
      "double arrow",
      "double dose",
      "double icon",
      "double line",
      "double size",
      "double tap",
      "duplicate",
      "font family",
      "quotation",
      "quote",
      "right",
      "right arrow",
      "serif",
      "serif font",
      "times",
      "typography"
    ]
  },
  "droplet": {
    "name": "Крапля",
    "mediaKey": "1a46d581-0349-4921-8842-8e3558fdc0c1",
    "keys": [
      "водяна крапля",
      "дроплет",
      "крапелька",
      "мала крапля",
      "міні крапля",
      "dew",
      "drop icon",
      "droplet",
      "droplet icon",
      "liquid bead",
      "liquid drop",
      "micro drop",
      "moisture drop",
      "teardrop",
      "tiny droplet",
      "water drop"
    ]
  },
  "eject": {
    "name": "Витягти",
    "mediaKey": "b094e267-1914-4852-b3fa-44001a918a44",
    "keys": [
      "вийняти медіа",
      "вийняти usb",
      "викинути",
      "витяг диска",
      "витягнути",
      "виштовхнути",
      "еджект",
      "disc eject",
      "eject",
      "eject button",
      "eject disk",
      "eject drive",
      "eject dvd",
      "eject icon",
      "eject key",
      "eject media"
    ]
  },
  "elevator": {
    "name": "Ліфт",
    "mediaKey": "ec36c83a-9360-4d67-b7ef-cbaca01c774a",
    "keys": [
      "елеватор",
      "кабіна ліфта",
      "ліфт",
      "ліфтова кабіна",
      "підйомник",
      "ascensor",
      "elevator",
      "elevator button",
      "elevator door",
      "elevator doors",
      "elevator lift",
      "elevator panel",
      "elevator pictogram",
      "elevator up",
      "lift elevator",
      "lift icon"
    ]
  },
  "ellipses": {
    "name": "Елліпси",
    "mediaKey": "dee073fd-7ea0-462e-830d-e429048736eb",
    "keys": [
      "...",
      "далі",
      "еліпси",
      "еліпсис",
      "контекстне меню",
      "три крапки",
      "ellipses",
      "ellipsis",
      "more menu",
      "more options"
    ]
  },
  "envelope-closed": {
    "name": "Конверт закритий",
    "mediaKey": "39c3dd3e-cbd4-4a82-aebd-614d9a97dd7b",
    "keys": [
      "закритий",
      "закрито",
      "замкнено",
      "клосед",
      "конверт",
      "лист",
      "повідомлення",
      "посилка",
      "пошта",
      "closed",
      "closed sign",
      "door shut",
      "email",
      "envelope",
      "mail",
      "mailbox"
    ]
  },
  "envelope-open": {
    "name": "Конверт відкритий",
    "mediaKey": "e0e3411c-59c1-45ae-834f-e9ebadb3d110",
    "keys": [
      "відкрити",
      "відкритий",
      "конверт",
      "лист",
      "опен",
      "повідомлення",
      "посилка",
      "пошта",
      "email",
      "envelope",
      "mail",
      "mailbox",
      "open",
      "open icon",
      "open state"
    ]
  },
  "euro": {
    "name": "Євро",
    "mediaKey": "af1065a2-ce48-448d-bcbf-f59877ff96ab",
    "keys": [
      "€",
      "валюта євро",
      "гроші",
      "еуро",
      "євро",
      "євро знак",
      "EU currency",
      "eur",
      "euro",
      "euro bill",
      "euro cash",
      "euro coins",
      "euro icon",
      "euro money",
      "european currency",
      "eurozone"
    ]
  },
  "excerpt": {
    "name": "Уривок",
    "mediaKey": "135f7e86-3bb2-4d86-be79-ec4764cf5f30",
    "keys": [
      "видобуток",
      "витяг",
      "уривок",
      "фрагмент",
      "частина",
      "excerpt",
      "highlight",
      "quote",
      "summary"
    ]
  },
  "expand-down": {
    "name": "Розгорнути вниз",
    "mediaKey": "1d76833d-6899-476e-9f85-cfbbc23d8b96",
    "keys": [
      "вниз",
      "довн",
      "експанд",
      "збільшити",
      "опустити",
      "розгорнути",
      "розширити",
      "рух донизу",
      "стрілка вниз",
      "arrow downwards",
      "descending arrow",
      "down",
      "down arrow",
      "down direction",
      "down icon",
      "down swipe",
      "download arrow",
      "downward",
      "expand",
      "expand arrows",
      "expand arrows icon",
      "expand icon",
      "expand layout",
      "expand view",
      "expand window",
      "full screen",
      "fullscreen",
      "grow area",
      "maximize",
      "move down",
      "open wider",
      "scroll down"
    ]
  },
  "expand-left": {
    "name": "Розгорнути ліворуч",
    "mediaKey": "199cf08c-a4cc-4063-8ea7-2a86c4c05599",
    "keys": [
      "←",
      "експанд",
      "збільшити",
      "зліва",
      "лефт",
      "ліва сторона",
      "лівий бік",
      "лівий напрямок",
      "розгорнути",
      "розширити",
      "arrow left",
      "expand",
      "expand arrows",
      "expand arrows icon",
      "expand icon",
      "expand layout",
      "expand view",
      "expand window",
      "full screen",
      "fullscreen",
      "grow area",
      "left",
      "left arrow",
      "maximize",
      "open wider",
      "west"
    ]
  },
  "expand-right": {
    "name": "Розгорнути праворуч",
    "mediaKey": "a5282867-5414-49c0-ba5c-539ccb48b860",
    "keys": [
      "експанд",
      "збільшити",
      "правильно",
      "праворуч",
      "ріґхт",
      "розгорнути",
      "розширити",
      "correct",
      "expand",
      "expand arrows",
      "expand arrows icon",
      "expand icon",
      "expand layout",
      "expand view",
      "expand window",
      "full screen",
      "fullscreen",
      "grow area",
      "maximize",
      "open wider",
      "right",
      "right arrow"
    ]
  },
  "expand-up": {
    "name": "Розгорнути вгору",
    "mediaKey": "172674fd-c5e3-4c99-9ff4-8c8e7206c032",
    "keys": [
      "ап",
      "вгору",
      "верх",
      "експанд",
      "збільшити",
      "підняти",
      "розгорнути",
      "розширити",
      "arrow up",
      "boost",
      "expand",
      "expand arrows",
      "expand arrows icon",
      "expand icon",
      "expand layout",
      "expand view",
      "expand window",
      "full screen",
      "fullscreen",
      "grow area",
      "maximize",
      "open wider",
      "up"
    ]
  },
  "external-link": {
    "name": "Зовнішнє посилання",
    "mediaKey": "fc51a67a-9e46-41a4-a164-56761824084b",
    "keys": [
      "віддалений",
      "гіперпосилання",
      "екстернал",
      "зв'язок",
      "ззовні",
      "зовнішній",
      "зовнішній ресурс",
      "лінк",
      "посилання",
      "chain",
      "external",
      "external access",
      "external arrow",
      "external icon",
      "external link",
      "external link icon",
      "external share",
      "hyperlink",
      "link",
      "link icon",
      "new window",
      "open in new tab",
      "outbound link",
      "outside resource",
      "url",
      "url-адреса"
    ]
  },
  "eye": {
    "name": "Око",
    "mediaKey": "b5fa60da-d3f9-4c9d-bcc0-3e57fc026fd1",
    "keys": [
      "👁️",
      "глянути",
      "еє",
      "око",
      "перегляд",
      "eye",
      "eye icon",
      "eye open",
      "preview",
      "see",
      "show password",
      "view",
      "view icon",
      "visibility",
      "watch",
      "watching"
    ]
  },
  "eyedropper": {
    "name": "Піпетка",
    "mediaKey": "2fc1cf71-5ff1-46cf-842a-13b62b6ff6a9",
    "keys": [
      "вибір кольору",
      "інструмент піпетка",
      "колір",
      "піпетка",
      "color picker",
      "eyedrop",
      "eyedropper",
      "palette",
      "sample color"
    ]
  },
  "file": {
    "name": "Файл",
    "mediaKey": "7120707c-4c4a-4716-9945-5faa74d775a3",
    "keys": [
      "файл",
      "філе",
      "data file",
      "digital file",
      "document file",
      "file",
      "file document",
      "file entry",
      "file icon",
      "file item",
      "file record"
    ]
  },
  "fire": {
    "name": "Вогонь",
    "mediaKey": "469c8e15-7c42-4d21-a656-5769db534e50",
    "keys": [
      "🔥",
      "вогонь",
      "полум'я",
      "фіре",
      "burn",
      "campfire",
      "fire",
      "fire emoji",
      "fire hazard",
      "fire icon",
      "flame"
    ]
  },
  "flag": {
    "name": "Прапор",
    "mediaKey": "8e2adb67-319b-4364-9577-cfac9739be67",
    "keys": [
      "🚩",
      "прапор",
      "прапорець",
      "флаґ",
      "banner",
      "bookmark flag",
      "country flag",
      "flag",
      "flag icon",
      "marker",
      "national flag"
    ]
  },
  "flash": {
    "name": "Flash",
    "mediaKey": "be5f0209-dbf9-4db2-98c8-3b49d2807752",
    "keys": [
      "adobe flash",
      "flash",
      "flash animation",
      "flash game",
      "flash icon",
      "flash light",
      "flash player",
      "lightning"
    ]
  },
  "folder": {
    "name": "Папка",
    "mediaKey": "f6c4007d-0b61-4691-8179-f0f36df141be",
    "keys": [
      "директорія",
      "каталог",
      "папка файлів",
      "папку",
      "фолдер",
      "file folder",
      "folder",
      "folder icon",
      "folder yellow"
    ]
  },
  "fork": {
    "name": "Виделка",
    "mediaKey": "8df9cbaf-0f2d-4b4e-bcd9-62270f98ba6f",
    "keys": [
      "вилка",
      "розгалуження",
      "столова вилка",
      "форк",
      "fork",
      "fork icon",
      "forked",
      "git fork",
      "utensil"
    ]
  },
  "fullscreen-enter": {
    "name": "Розгорнути на весь екран",
    "mediaKey": "8f70a9b3-0ef1-4bc6-8491-2b282662659d",
    "keys": [
      "↵",
      "введіть",
      "ввести",
      "вхід",
      "ентер",
      "клавіша enter",
      "натисніть enter",
      "перейти",
      "повний екран",
      "фулскрін",
      "enter",
      "enter arrow",
      "enter button",
      "enter confirm",
      "enter key",
      "enter submit",
      "full view",
      "fullscreen",
      "keyboard enter",
      "maximize",
      "submit"
    ]
  },
  "fullscreen-exit": {
    "name": "Вихід з повного екрана",
    "mediaKey": "4ea892a2-94b3-4b3b-9afe-b078dc41955b",
    "keys": [
      "вийти",
      "вийти назовні",
      "вихід",
      "ексіт",
      "кнопка виход",
      "повний екран",
      "фулскрін",
      "emergency exit",
      "escape",
      "exit",
      "exit arrow",
      "exit door",
      "exit door sign",
      "exit icon",
      "exit sign",
      "full view",
      "fullscreen",
      "leave",
      "logout",
      "maximize",
      "salida"
    ]
  },
  "globe": {
    "name": "Глобус",
    "mediaKey": "eb20df31-f73a-4c15-acb8-0cd04445cf3d",
    "keys": [
      "🌍",
      "глобус",
      "ґлобе",
      "earth",
      "global icon",
      "globe",
      "world"
    ]
  },
  "graph": {
    "name": "Графік",
    "mediaKey": "33c76215-4770-4349-b0b3-d1478903122a",
    "keys": [
      "графік",
      "ґраф",
      "chart",
      "diagram",
      "graph",
      "graph icon",
      "plot"
    ]
  },
  "grid-four-up": {
    "name": "Сітка 4x",
    "mediaKey": "96766859-199f-4494-b4b0-ab6cd7e3cba7",
    "keys": [
      "альта",
      "ап",
      "блокчейн",
      "валюта",
      "вгору",
      "верх",
      "ґрід",
      "коін",
      "крипта",
      "криптовалюта",
      "монета",
      "підняти",
      "решітка",
      "сітка",
      "сітка 3х3",
      "токен",
      "arrow up",
      "blockchain",
      "boost",
      "coin",
      "crypto",
      "cryptocurrency",
      "four",
      "grid",
      "grid icon",
      "grid layout",
      "token",
      "up"
    ]
  },
  "grid-three-up": {
    "name": "Сітка 3x",
    "mediaKey": "20e5fcd9-a1a3-47be-838c-ec7c6fa77bd0",
    "keys": [
      "3️⃣",
      "ап",
      "вгору",
      "верх",
      "ґрід",
      "підняти",
      "решітка",
      "сітка",
      "сітка 3х3",
      "третє",
      "три",
      "трійка",
      "цифра 3",
      "arrow up",
      "boost",
      "grid",
      "grid icon",
      "grid layout",
      "number three",
      "three",
      "up"
    ]
  },
  "grid-two-up": {
    "name": "Сітка 2x",
    "mediaKey": "97967354-a7e4-4a79-a55e-e3d1838eb375",
    "keys": [
      "2️⃣",
      "ап",
      "вгору",
      "верх",
      "ґрід",
      "два",
      "двійка",
      "підняти",
      "решітка",
      "сітка",
      "сітка 3х3",
      "цифра 2",
      "arrow up",
      "boost",
      "grid",
      "grid icon",
      "grid layout",
      "number two",
      "pair",
      "two",
      "up"
    ]
  },
  "hard-drive": {
    "name": "Накопичувач",
    "mediaKey": "ac5936fc-1ec9-470b-8729-fae7981ec960",
    "keys": [
      "важко",
      "диск",
      "дріве",
      "жорсткий диск",
      "накопичувач",
      "складно",
      "твердо",
      "cloud drive",
      "disk storage",
      "drive",
      "drive backup",
      "drive folder",
      "drive icon",
      "drive letter",
      "external drive",
      "hard",
      "hard drive",
      "network drive",
      "solid",
      "storage device",
      "storage drive"
    ]
  },
  "header": {
    "name": "Заголовок",
    "mediaKey": "97ffe537-e0d0-4b61-a8de-7521de32f2c0",
    "keys": [
      "верх сторінки",
      "верхня панель",
      "заголовок",
      "меню",
      "навігація",
      "панель",
      "шапка",
      "banner",
      "head",
      "header",
      "header section",
      "title",
      "top bar"
    ]
  },
  "headphones": {
    "name": "Навушники",
    "mediaKey": "364ec6d1-4456-4b09-977a-a63c87405c64",
    "keys": [
      "🎧",
      "навушники",
      "хеадфонес",
      "audio headset",
      "earphones",
      "headphone icon",
      "headphones"
    ]
  },
  "heart": {
    "name": "Серце",
    "mediaKey": "f2ac1bc5-a3aa-4436-badd-426b6cd3c4a0",
    "keys": [
      "❤️",
      "кохання",
      "серце",
      "хеарт",
      "heart",
      "heart icon",
      "love"
    ]
  },
  "home": {
    "name": "Будинок",
    "mediaKey": "54e3e33f-d523-43aa-9901-6b44c924c0f9",
    "keys": [
      "🏠",
      "дім",
      "додому",
      "хоме",
      "home",
      "homepage",
      "house icon"
    ]
  },
  "image": {
    "name": "Зображення",
    "mediaKey": "a725b80a-77a7-4987-8aee-665577776b47",
    "keys": [
      "зображення",
      "імаґе",
      "фото",
      "graphic",
      "image",
      "image file",
      "picture"
    ]
  },
  "inbox": {
    "name": "Вхідні",
    "mediaKey": "fa9993fb-1c91-4398-9f67-5827dd646fbf",
    "keys": [
      "вхідні",
      "вхідні листи",
      "інбокс",
      "email inbox",
      "inbox",
      "inbox tray",
      "mailbox"
    ]
  },
  "infinity": {
    "name": "Нескінченність",
    "mediaKey": "ecaf60ed-e256-4811-9635-6e3eb59ac907",
    "keys": [
      "∞",
      "безмежність",
      "інфінітй",
      "нескінченність",
      "forever",
      "infinite loop",
      "infinity"
    ]
  },
  "info": {
    "name": "Інформація",
    "mediaKey": "078848f5-dce0-4eb9-a38b-2d65d399a2ec",
    "keys": [
      "інфо",
      "інформація",
      "details",
      "ℹ️",
      "info",
      "info icon",
      "information"
    ]
  },
  "italic": {
    "name": "Курсив",
    "mediaKey": "9c7e6945-9dfb-4f3c-9370-d8d0e0cf3a9b",
    "keys": [
      "італік",
      "курсив",
      "курсивний текст",
      "italic",
      "italic font",
      "italic style",
      "italicize"
    ]
  },
  "justify-center": {
    "name": "Вирівняти по центру",
    "mediaKey": "1b45de66-cb01-481c-b8a1-094a045bb11e",
    "keys": [
      "вирівняти",
      "кентер",
      "текст по ширині",
      "типографія",
      "центр",
      "центрування",
      "alignment",
      "center",
      "center align",
      "format",
      "justify",
      "justify text",
      "middle",
      "text align"
    ]
  },
  "justify-left": {
    "name": "Вирівняти ліворуч",
    "mediaKey": "83a69305-8586-4d96-afd5-03e20a57ff39",
    "keys": [
      "←",
      "вирівняти",
      "зліва",
      "лефт",
      "ліва сторона",
      "лівий бік",
      "лівий напрямок",
      "текст по ширині",
      "типографія",
      "alignment",
      "arrow left",
      "format",
      "justify",
      "justify text",
      "left",
      "left arrow",
      "text align",
      "west"
    ]
  },
  "justify-right": {
    "name": "Вирівняти праворуч",
    "mediaKey": "878e4d07-c035-4166-8ea7-7fa664ad022c",
    "keys": [
      "вирівняти",
      "правильно",
      "праворуч",
      "ріґхт",
      "текст по ширині",
      "типографія",
      "alignment",
      "correct",
      "format",
      "justify",
      "justify text",
      "right",
      "right arrow",
      "text align"
    ]
  },
  "key": {
    "name": "Ключ",
    "mediaKey": "95003310-e49f-43f8-8970-d77cabd1b910",
    "keys": [
      "🔑",
      "кей",
      "ключ",
      "ключ іконка",
      "key",
      "key symbol",
      "unlock"
    ]
  },
  "laptop": {
    "name": "Ноутбук",
    "mediaKey": "ddb059c0-4930-46c1-bc98-ce6862eb17b4",
    "keys": [
      "лаптоп",
      "ноут",
      "ноутбук",
      "портативний комп'ютер",
      "laptop",
      "laptop icon",
      "notebook",
      "portable pc",
      "workstation"
    ]
  },
  "layers": {
    "name": "Шари",
    "mediaKey": "e061f127-b860-4fef-a41d-be4a3d0fd5f1",
    "keys": [
      "лаєрс",
      "рівні",
      "шари",
      "шаровість",
      "layer icon",
      "layer stack",
      "layers",
      "overlay",
      "photoshop layers"
    ]
  },
  "lightbulb": {
    "name": "Лампочка",
    "mediaKey": "5ab91b56-9099-499a-b8fb-e9791f0bd18f",
    "keys": [
      "ідея",
      "лампа",
      "лампочка",
      "idea",
      "lightbulb"
    ]
  },
  "link-broken": {
    "name": "Розірване посилання",
    "mediaKey": "99432238-1f0e-4de1-a956-2333d5b807f3",
    "keys": [
      "брокен",
      "гіперпосилання",
      "зв'язок",
      "зламаний",
      "лінк",
      "посилання",
      "пошкоджено",
      "broken",
      "broken link",
      "chain",
      "cracked",
      "hyperlink",
      "link",
      "link icon",
      "url",
      "url-адреса"
    ]
  },
  "link-intact": {
    "name": "Ціле посилання",
    "mediaKey": "2901c15c-f837-4161-b1c6-c916295fac35",
    "keys": [
      "бренд",
      "гіперпосилання",
      "зв'язок",
      "лінк",
      "логотип",
      "посилання",
      "цілий",
      "chain",
      "hyperlink",
      "intact",
      "link",
      "link icon",
      "url",
      "url-адреса"
    ]
  },
  "list": {
    "name": "Список",
    "mediaKey": "d3f06255-c97f-4f76-aaf9-52ebc6b4aaeb",
    "keys": [
      "каталог",
      "ліст",
      "перелік",
      "список",
      "bulleted list",
      "enumeration",
      "list",
      "listing",
      "todo list"
    ]
  },
  "list-rich": {
    "name": "Розширений список",
    "mediaKey": "c63a7b33-c8e5-4f88-a84a-63c177247eed",
    "keys": [
      "багатий",
      "каталог",
      "ліст",
      "насичений",
      "перелік",
      "преміум",
      "список",
      "bulleted list",
      "deluxe",
      "enumeration",
      "fat",
      "full",
      "list",
      "listing",
      "luxury",
      "opulent",
      "rich",
      "todo list",
      "wealthy"
    ]
  },
  "location": {
    "name": "Локація",
    "mediaKey": "029f9b72-cdf0-4509-af97-7bab354e7566",
    "keys": [
      "геолокація",
      "геопозиція",
      "координати",
      "локатіон",
      "локація",
      "місце",
      "місце знаходження",
      "місцеположення",
      "розташування",
      "location",
      "map location",
      "pin на мапі"
    ]
  },
  "lock-locked": {
    "name": "Замок зачинено",
    "mediaKey": "a0df6461-5923-4530-a181-de5332f94c29",
    "keys": [
      "блокування",
      "заблоковано",
      "закритий доступ",
      "закрито",
      "замикання",
      "замкнено",
      "замкнути",
      "замок",
      "замок безпеки",
      "локк",
      "падлок",
      "lock",
      "locked",
      "security"
    ]
  },
  "lock-unlocked": {
    "name": "Замок відчинено",
    "mediaKey": "d87e39a2-7f33-43f6-8534-5c79d1719664",
    "keys": [
      "блокування",
      "відімкнено",
      "відкрито",
      "вільно",
      "заблоковано",
      "закритий доступ",
      "замикання",
      "замкнути",
      "замок",
      "замок безпеки",
      "локк",
      "падлок",
      "розблоковано",
      "lock",
      "open lock",
      "security",
      "unlocked"
    ]
  },
  "loop": {
    "name": "Петля",
    "mediaKey": "e5f5dbc3-b4df-4bb8-abb3-d958ceaaba3a",
    "keys": [
      "зациклити",
      "лооп",
      "петля",
      "повторення",
      "повторюваність",
      "цикл",
      "циклічний рух",
      "loop",
      "looping",
      "repeat"
    ]
  },
  "loop-circular": {
    "name": "Кругова петля",
    "mediaKey": "9295534f-62b1-45e5-9c44-7703bfbc63bc",
    "keys": [
      "зациклити",
      "круговий",
      "лооп",
      "обертання",
      "округлий",
      "петля",
      "по колу",
      "повторення",
      "повторюваність",
      "цикл",
      "циклічний",
      "циклічний рух",
      "circle",
      "circular",
      "loop",
      "looping",
      "repeat",
      "round"
    ]
  },
  "loop-square": {
    "name": "Цикл квадрат",
    "mediaKey": "c6296ada-b217-4acc-a899-9484942cd9bc",
    "keys": [
      "зациклити",
      "касовий термінал",
      "квад",
      "квадрат",
      "лооп",
      "петля",
      "платіжна система Square",
      "плитка",
      "площа",
      "площі",
      "повторення",
      "повторюваність",
      "фігура 4x4",
      "цикл",
      "циклічний рух",
      "loop",
      "looping",
      "repeat",
      "square",
      "Square",
      "Squareup"
    ]
  },
  "magnifying-glass": {
    "name": "Лупа",
    "mediaKey": "e7bb90c4-06da-4d9e-aede-e1aed6a18815",
    "keys": [
      "ґласс",
      "збільшення",
      "зум",
      "лупа",
      "скло",
      "enlarge",
      "glass",
      "glass icon",
      "glass material",
      "glass pane",
      "magnifier",
      "magnifying",
      "search",
      "transparent",
      "zoom"
    ]
  },
  "map": {
    "name": "Карта",
    "mediaKey": "a91df701-7a02-4af5-acb2-f749637ec357",
    "keys": [
      "карта",
      "карта місцевості",
      "мап",
      "мапа",
      "map",
      "map pin"
    ]
  },
  "map-marker": {
    "name": "Маркер карти",
    "mediaKey": "216c3f2f-1275-48ce-952b-7a70849ffbad",
    "keys": [
      "карта",
      "карта місцевості",
      "мап",
      "мапа",
      "маркер",
      "позначити",
      "позначка",
      "highlight",
      "label",
      "map",
      "map pin",
      "marker",
      "notation",
      "pin",
      "tag"
    ]
  },
  "media-pause": {
    "name": "Пауза",
    "mediaKey": "d4d4e5c5-6494-4379-9753-d6c401a439af",
    "keys": [
      "⏸️",
      "аудіо",
      "відео",
      "контент",
      "медіа",
      "пауза",
      "паусе",
      "призупинити",
      "media",
      "media hub",
      "pause",
      "pause icon",
      "press",
      "stream"
    ]
  },
  "media-play": {
    "name": "Відтворення",
    "mediaKey": "9bb04c2d-beb8-4c24-bc27-605972239cfc",
    "keys": [
      "▶️",
      "аудіо",
      "відео",
      "грати",
      "контент",
      "медіа",
      "плай",
      "media",
      "media hub",
      "play",
      "play button",
      "press",
      "stream"
    ]
  },
  "media-record": {
    "name": "Запис",
    "mediaKey": "8fb61cda-0ef0-4b86-97dd-cefe5fefb04b",
    "keys": [
      "аудіо",
      "відео",
      "запис",
      "контент",
      "медіа",
      "рекорд",
      "media",
      "media hub",
      "press",
      "record",
      "record audio",
      "record button",
      "stream"
    ]
  },
  "media-skip-backward": {
    "name": "Пропустити назад",
    "mediaKey": "728206dd-f6ec-4228-8b4c-31edcdd19992",
    "keys": [
      "аудіо",
      "бакквард",
      "відео",
      "далі",
      "задній хід",
      "контент",
      "медіа",
      "назад",
      "перескочити",
      "проминути",
      "пропустити",
      "скип",
      "backward",
      "media",
      "media hub",
      "next",
      "omit",
      "press",
      "reverse",
      "rewind",
      "skip",
      "stream"
    ]
  },
  "media-skip-forward": {
    "name": "Пропустити вперед",
    "mediaKey": "8a7186e5-6fc6-4b71-b483-451e42c0d838",
    "keys": [
      "аудіо",
      "відео",
      "вперед",
      "далі",
      "контент",
      "медіа",
      "направити вперед",
      "перескочити",
      "переслати",
      "проминути",
      "пропустити",
      "скип",
      "форвард",
      "ahead",
      "fast forward",
      "forward",
      "forward arrow",
      "forward icon",
      "media",
      "media hub",
      "next",
      "omit",
      "press",
      "skip",
      "stream"
    ]
  },
  "media-step-backward": {
    "name": "Крок назад (медіа)",
    "mediaKey": "52a2d1cf-4a1e-4997-8991-44dca25b9871",
    "keys": [
      "аудіо",
      "бакквард",
      "відео",
      "етап",
      "задній хід",
      "контент",
      "крок",
      "крок вперед",
      "медіа",
      "назад",
      "степ",
      "ступінь",
      "backward",
      "media",
      "media hub",
      "press",
      "reverse",
      "rewind",
      "stage",
      "step",
      "stream"
    ]
  },
  "media-step-forward": {
    "name": "Крок вперед (медіа)",
    "mediaKey": "2916475c-8f44-442b-b946-9d68328d3e6e",
    "keys": [
      "аудіо",
      "відео",
      "вперед",
      "етап",
      "контент",
      "крок",
      "крок вперед",
      "медіа",
      "направити вперед",
      "переслати",
      "степ",
      "ступінь",
      "форвард",
      "ahead",
      "fast forward",
      "forward",
      "forward arrow",
      "forward icon",
      "media",
      "media hub",
      "press",
      "stage",
      "step",
      "stream"
    ]
  },
  "media-stop": {
    "name": "Зупинити медіа",
    "mediaKey": "ccd07ec4-ef8a-4ec5-8d64-56f14a41e0ac",
    "keys": [
      "аудіо",
      "відео",
      "заборона",
      "зупинити",
      "зупинка",
      "контент",
      "медіа",
      "пауза",
      "стоп",
      "стопкадр",
      "halt",
      "media",
      "media hub",
      "press",
      "stop",
      "stream"
    ]
  },
  "medical-cross": {
    "name": "Хрест медичний",
    "mediaKey": "d893451e-6d06-4304-8ca6-e71c7853180b",
    "keys": [
      "закрити",
      "кросс",
      "медична сфера",
      "медичний",
      "медікал",
      "охорона здоров'я",
      "перехрестя",
      "хрест",
      "хрестик",
      "cross",
      "cross icon",
      "healthcare",
      "medical"
    ]
  },
  "menu": {
    "name": "Меню",
    "mediaKey": "5fd24d07-fbd4-4a5e-b203-b4ba2d25a0a0",
    "keys": [
      "мену",
      "меню",
      "менюшка",
      "навігаційне меню",
      "список страв",
      "dropdown menu",
      "menu"
    ]
  },
  "microphone": {
    "name": "Мікрофон",
    "mediaKey": "146dd627-732c-41d7-a771-d791c06ee601",
    "keys": [
      "🎙️",
      "мікрофон",
      "мікрофоне",
      "мікрофончик",
      "mic",
      "microphone",
      "voice recording"
    ]
  },
  "minus": {
    "name": "Мінус",
    "mediaKey": "e57718a3-3a5d-4ec5-8c19-cfd4664857b8",
    "keys": [
      "відняти",
      "знак мінус",
      "мінус",
      "minus",
      "negative",
      "subtract"
    ]
  },
  "monitor": {
    "name": "Монітор",
    "mediaKey": "aa06d01c-c03a-4dd3-8fea-70f6978acce3",
    "keys": [
      "екран комп'ютера",
      "монітор",
      "display screen",
      "monitor",
      "monitor icon"
    ]
  },
  "moon": {
    "name": "Місяць",
    "mediaKey": "acf52a09-8a72-4a5b-b73b-3bf8754adef4",
    "keys": [
      "🌙",
      "луна",
      "місяць",
      "моон",
      "супутник Землі",
      "moon"
    ]
  },
  "move": {
    "name": "Переміщення",
    "mediaKey": "6d4bbe58-dd9c-45f4-b260-6edaccbc8128",
    "keys": [
      "мове",
      "перемістити",
      "пересування",
      "рухатися",
      "drag",
      "move",
      "move tool"
    ]
  },
  "musical-note": {
    "name": "Нота",
    "mediaKey": "3bc37eb8-60f0-461f-848d-40ebb104ce2d",
    "keys": [
      "музичний",
      "нотатка",
      "ноте",
      "ноти",
      "примітка",
      "concert",
      "melody",
      "music",
      "musical",
      "note",
      "note pad",
      "song",
      "sound",
      "sticky note"
    ]
  },
  "paperclip": {
    "name": "Скріпка",
    "mediaKey": "2ca5fe0e-c085-4e7c-aabc-765de1dd62b3",
    "keys": [
      "канцелярська",
      "канцелярська скріпка",
      "паперкліп",
      "скріпка",
      "clip icon",
      "office clip",
      "paperclip"
    ]
  },
  "pencil": {
    "name": "Олівець",
    "mediaKey": "ae626eaa-5db3-4afa-acc2-ff5d9b6c736f",
    "keys": [
      "малювати",
      "олівець",
      "пенкіл",
      "pencil",
      "pencil icon"
    ]
  },
  "people": {
    "name": "People",
    "mediaKey": "d2a290a7-d1c8-48f3-8ed7-195e3125d353",
    "keys": [
      "альта",
      "блокчейн",
      "валюта",
      "коін",
      "крипта",
      "криптовалюта",
      "монета",
      "токен",
      "blockchain",
      "coin",
      "crypto",
      "cryptocurrency",
      "people",
      "token"
    ]
  },
  "person": {
    "name": "Людина",
    "mediaKey": "837b80cb-26b1-426a-8ecb-689742fa543f",
    "keys": [
      "користувач",
      "людина",
      "профіль",
      "account",
      "avatar",
      "human",
      "person",
      "profile",
      "user"
    ]
  },
  "phone": {
    "name": "Телефон",
    "mediaKey": "5728e858-aeae-46c9-99c7-11fdac190f6b",
    "keys": [
      "телефон",
      "фоне",
      "handset",
      "phone",
      "phone call"
    ]
  },
  "pie-chart": {
    "name": "Кругова діаграма",
    "mediaKey": "8da99536-044c-4fd4-9ab7-2bc2e6e1cf80",
    "keys": [
      "графік",
      "діаграма",
      "пиріг",
      "піе",
      "чарт",
      "chart",
      "chart icon",
      "pie",
      "pie chart",
      "slice",
      "stats"
    ]
  },
  "pin": {
    "name": "Шпилька",
    "mediaKey": "fed45489-3de2-43f2-9b5e-1b3deb88e595",
    "keys": [
      "закріпити",
      "пін",
      "шпилька",
      "pin",
      "pin icon"
    ]
  },
  "play-circle": {
    "name": "Відтворення в колі",
    "mediaKey": "404ab6b8-7fba-4948-8f91-5b5d982fc813",
    "keys": [
      "▶️",
      "грати",
      "кіркле",
      "коло",
      "окружність",
      "плай",
      "circle",
      "circle shape",
      "play",
      "play button",
      "round"
    ]
  },
  "plus": {
    "name": "Плюс",
    "mediaKey": "9126ec05-75fb-4e4f-b940-acf0432fe9f6",
    "keys": [
      "+",
      "додати",
      "плус",
      "плюс",
      "plus",
      "positive"
    ]
  },
  "power-standby": {
    "name": "Режим очікування",
    "mediaKey": "7fc1d330-a8c4-466e-b880-9987c2d4c716",
    "keys": [
      "живлення",
      "повер",
      "потужність",
      "режим очікування",
      "стендбай",
      "idle",
      "low power",
      "pause",
      "power",
      "power button",
      "rest",
      "sleep",
      "standby",
      "wait"
    ]
  },
  "print": {
    "name": "Друк",
    "mediaKey": "2e67bd1d-e2b1-47e5-983f-6416b5021e66",
    "keys": [
      "друк",
      "надрукувати",
      "принтер",
      "роздруківка",
      "роздрукувати",
      "hardcopy",
      "pdf",
      "pdf export",
      "print",
      "print icon",
      "print out",
      "printer",
      "printout"
    ]
  },
  "project": {
    "name": "Проєкт",
    "mediaKey": "5b6b4ff1-055e-4859-aed7-1c27d8d5fbc4",
    "keys": [
      "задача",
      "план",
      "проєкт",
      "board",
      "case",
      "initiative",
      "project",
      "roadmap",
      "workspace"
    ]
  },
  "pulse": {
    "name": "Пульс",
    "mediaKey": "d50d4673-8b38-4ada-b0ed-d49e366d23e9",
    "keys": [
      "бієння",
      "пульс",
      "ритм",
      "серце",
      "heartbeat",
      "medical",
      "pulse",
      "pulse rate"
    ]
  },
  "puzzle-piece": {
    "name": "Фрагмент пазла",
    "mediaKey": "5847f18e-68dc-45c4-8999-cc92782745e5",
    "keys": [
      "головоломка",
      "пуззле",
      "фрагмент",
      "частина",
      "шматок",
      "bit",
      "jigsaw",
      "piece",
      "puzzle",
      "puzzle game",
      "segment"
    ]
  },
  "question-mark": {
    "name": "Знак питання",
    "mediaKey": "91c658fb-6659-4340-95c9-15425a448c1b",
    "keys": [
      "?",
      "запитання",
      "знак",
      "квестіон",
      "марк",
      "мітка",
      "питання",
      "позначка",
      "mark",
      "marker",
      "question",
      "question mark"
    ]
  },
  "rain": {
    "name": "Дощ",
    "mediaKey": "8485815f-55d7-48e7-8a12-82ccd22f0a4f",
    "keys": [
      "🌧️",
      "дощ",
      "раін",
      "rain",
      "rainy"
    ]
  },
  "random": {
    "name": "Випадково",
    "mediaKey": "15a46b03-17fb-4275-8802-e8052bd1594b",
    "keys": [
      "випадковий",
      "рандом",
      "random",
      "shuffle"
    ]
  },
  "reload": {
    "name": "Перезавантажити",
    "mediaKey": "70e5b9ff-2a94-461f-b42c-2cdea0b8815c",
    "keys": [
      "перезавантажити",
      "релоад",
      "refresh page",
      "reload",
      "reload icon"
    ]
  },
  "resize-both": {
    "name": "Змінити розмір обох",
    "mediaKey": "cc7aa75b-796a-4a51-b5e2-5998d711de97",
    "keys": [
      "бот",
      "дві опції",
      "змінити",
      "змінити розмір",
      "обидва",
      "одночасно",
      "ресізе",
      "розмір",
      "both",
      "both sides",
      "rescale",
      "resize",
      "resize handle"
    ]
  },
  "resize-height": {
    "name": "Змінити висоту",
    "mediaKey": "0a627eb2-b86d-4563-895e-a1071f17a45a",
    "keys": [
      "висота",
      "височина",
      "змінити",
      "змінити розмір",
      "ресізе",
      "ріст",
      "розмір",
      "хеіґхт",
      "height",
      "height value",
      "rescale",
      "resize",
      "resize handle",
      "vertical size"
    ]
  },
  "resize-width": {
    "name": "Змінити ширину",
    "mediaKey": "c5299b92-d675-42da-8db6-84bf77d251fd",
    "keys": [
      "змінити",
      "змінити розмір",
      "ресізе",
      "розмір",
      "ширина",
      "ширина блоку",
      "широчінь",
      "dimension",
      "rescale",
      "resize",
      "resize handle",
      "span",
      "width"
    ]
  },
  "rss": {
    "name": "Стрічка RSS",
    "mediaKey": "ff0a6626-71d1-487d-8422-b699cccd1627",
    "keys": [
      "рсс",
      "стрічка RSS",
      "rss",
      "RSS feed",
      "rss icon"
    ]
  },
  "rss-alt": {
    "name": "RSS (альт)",
    "mediaKey": "9385b9fa-494e-4ade-8b36-897ba1bdc4b2",
    "keys": [
      "алт",
      "альт",
      "альтернативний текст",
      "рсс",
      "стрічка RSS",
      "alt",
      "alt клавіша",
      "alt key",
      "modifier key",
      "rss",
      "RSS feed",
      "rss icon"
    ]
  },
  "script": {
    "name": "Скрипт",
    "mediaKey": "360d5592-3aa1-4cb8-9e6c-d0c0af5c9193",
    "keys": [
      "скрипт",
      "скріпт",
      "сценарій",
      "automation",
      "script",
      "script file"
    ]
  },
  "share": {
    "name": "Поділ",
    "mediaKey": "149e497d-8929-4bee-99dc-6f557ed42116",
    "keys": [
      "поділ",
      "поділитися",
      "поширити",
      "поширити 🔗",
      "розшарити",
      "частка",
      "шер",
      "шерінг",
      "distribute",
      "share"
    ]
  },
  "share-boxed": {
    "name": "Поділитися (в рамці)",
    "mediaKey": "35b4e8d6-66b5-405d-9d35-30d2d843b74c",
    "keys": [
      "контейнер",
      "обведено",
      "пакунок",
      "поділ",
      "поділитися",
      "поширити",
      "поширити 🔗",
      "рамка",
      "розшарити",
      "у коробці",
      "у рамці",
      "частка",
      "шер",
      "шерінг",
      "box",
      "boxed",
      "boxed icon",
      "distribute",
      "package",
      "share"
    ]
  },
  "shield": {
    "name": "Щит",
    "mediaKey": "54be7682-567a-4a9d-868e-a6c89593bb6c",
    "keys": [
      "🛡️",
      "броня",
      "герб",
      "емблема",
      "захист",
      "шіелд",
      "щит",
      "guard",
      "protect",
      "shield"
    ]
  },
  "signal": {
    "name": "Сигнал",
    "mediaKey": "ae05ecd1-6fa6-489f-9e99-eeb7d706f37e",
    "keys": [
      "зв'язок",
      "індикатор",
      "передавач",
      "повідомлення",
      "сигнал",
      "сіґнал",
      "beacon",
      "signal"
    ]
  },
  "signpost": {
    "name": "Вказівник",
    "mediaKey": "6c1f4d91-c579-41cb-b747-50741890809f",
    "keys": [
      "вказівник",
      "дороговказ",
      "arrow",
      "direction",
      "guide",
      "road sign",
      "sign",
      "signpost",
      "wayfinding"
    ]
  },
  "sort-ascending": {
    "name": "Сортувати за зростанням",
    "mediaKey": "69223ae2-51d3-4572-be09-84f92229f7bb",
    "keys": [
      "а-я",
      "аскендінґ",
      "висхідний",
      "від меншого до більшого",
      "відсіяти",
      "групувати",
      "за зростанням",
      "сорт",
      "сортування",
      "сортувати",
      "упорядкувати",
      "фільтрувати",
      "ascending",
      "ascending order",
      "filter",
      "order",
      "sort"
    ]
  },
  "sort-descending": {
    "name": "Сортувати за спаданням",
    "mediaKey": "8d5980e9-f155-4352-8c12-7c82d765797f",
    "keys": [
      "від більшого до меншого",
      "відсіяти",
      "групувати",
      "дескендінґ",
      "зменшення",
      "низхідний",
      "сорт",
      "сортування",
      "сортування за спаданням",
      "сортувати",
      "спадання",
      "спадаючий список",
      "спадна послідовність",
      "спадний напрямок",
      "спуск",
      "упорядкувати",
      "фільтрувати",
      "descending",
      "descending arrow",
      "descending order",
      "descending sort",
      "downward",
      "falling order",
      "filter",
      "order",
      "sort"
    ]
  },
  "spreadsheet": {
    "name": "Таблиця",
    "mediaKey": "b11a013c-7c50-492e-969c-7c4f5bf9b270",
    "keys": [
      "електронна таблиця",
      "таблиця",
      "табличка",
      "Excel",
      "Google Sheets",
      "grid",
      "sheet",
      "spreadsheet"
    ]
  },
  "star": {
    "name": "Зірка",
    "mediaKey": "824f8b74-36a6-4f46-bf33-4e4863e4ef97",
    "keys": [
      "⭐",
      "відмітити",
      "зірка",
      "зоря",
      "улюблене",
      "favorite",
      "star"
    ]
  },
  "sun": {
    "name": "Сонце",
    "mediaKey": "ab3149c9-0b85-4cb6-be13-4fd43644cd24",
    "keys": [
      "☀️",
      "денне світло",
      "світило",
      "соляр",
      "сонце",
      "тепло",
      "sun"
    ]
  },
  "tablet": {
    "name": "Планшет",
    "mediaKey": "bf74cf6d-e8bb-41f6-9f1c-96fe0780a593",
    "keys": [
      "планшет",
      "планшетний комп'ютер",
      "таблет",
      "тач-пристрій",
      "e-reader",
      "tablet",
      "tablet pc"
    ]
  },
  "tag": {
    "name": "Тег",
    "mediaKey": "6029eada-8fc5-4727-afc4-8b5ae0c585f6",
    "keys": [
      "мітка",
      "тег",
      "хештег",
      "ярлик",
      "label",
      "mark",
      "tag"
    ]
  },
  "tags": {
    "name": "Теги",
    "mediaKey": "83d717e0-dc63-474f-8047-808e510a65a3",
    "keys": [
      "мітки",
      "теги",
      "хештеги",
      "ярлики",
      "keywords",
      "labels",
      "tags"
    ]
  },
  "target": {
    "name": "Мішень",
    "mediaKey": "6355223e-9c18-42f3-b753-452a170c3dce",
    "keys": [
      "магазин Target",
      "мета",
      "мішень",
      "приціл",
      "ціль",
      "aim",
      "goal",
      "target"
    ]
  },
  "task": {
    "name": "Завдання",
    "mediaKey": "a649bde6-5a18-4957-8a15-88b8f5a010d2",
    "keys": [
      "завдання",
      "таска",
      "issue",
      "task",
      "todo"
    ]
  },
  "terminal": {
    "name": "Термінал",
    "mediaKey": "ec5a90b7-b961-4406-aca4-2bae3af9ef11",
    "keys": [
      "аеропорт",
      "командний рядок",
      "консоль",
      "порт",
      "термінал",
      "CLI",
      "terminal"
    ]
  },
  "text": {
    "name": "Текст",
    "mediaKey": "3e41fc71-5be0-413d-8617-3e72db66c017",
    "keys": [
      "абзац",
      "копірайт",
      "повідомлення",
      "текст",
      "content",
      "copy",
      "text"
    ]
  },
  "thumb-down": {
    "name": "Великий палець вниз",
    "mediaKey": "ab4101d7-0f39-437b-adb6-90b1b6fc828b",
    "keys": [
      "великий палець",
      "відбиток",
      "вниз",
      "довн",
      "лайк",
      "мініатюра",
      "опустити",
      "рух донизу",
      "стрілка вниз",
      "arrow downwards",
      "descending arrow",
      "down",
      "down arrow",
      "down direction",
      "down icon",
      "down swipe",
      "download arrow",
      "downward",
      "move down",
      "scroll down",
      "thumb",
      "thumbnail",
      "thumbs up"
    ]
  },
  "thumb-up": {
    "name": "Великий палець вгору",
    "mediaKey": "b4f1141e-a7a7-47ea-81d3-56fb86dba5c0",
    "keys": [
      "ап",
      "вгору",
      "великий палець",
      "верх",
      "відбиток",
      "лайк",
      "мініатюра",
      "підняти",
      "arrow up",
      "boost",
      "thumb",
      "thumbnail",
      "thumbs up",
      "up"
    ]
  },
  "timer": {
    "name": "Таймер",
    "mediaKey": "8e645cda-597b-4c1b-a216-d9ecffdf16a7",
    "keys": [
      "відлік",
      "секундомір",
      "таймер",
      "chronometer",
      "clock",
      "countdown",
      "time",
      "timer"
    ]
  },
  "transfer": {
    "name": "Передача",
    "mediaKey": "e397534c-2835-4584-a4dd-7c4afbe65d30",
    "keys": [
      "передача",
      "переказ",
      "перенос",
      "трансфер",
      "move",
      "send",
      "transfer"
    ]
  },
  "trash": {
    "name": "Сміття",
    "mediaKey": "16080b64-20ee-4ee2-bb28-f07a3c330040",
    "keys": [
      "видалити",
      "корзина",
      "кошик",
      "сміття",
      "bin",
      "delete",
      "trash"
    ]
  },
  "underline": {
    "name": "Підкреслення",
    "mediaKey": "75eb72dc-6e33-4f32-b77a-8194d5a69ded",
    "keys": [
      "лінія знизу",
      "підкреслення",
      "підкреслити",
      "форматування",
      "highlight",
      "underline",
      "underlined",
      "underscore"
    ]
  },
  "vertical-align-bottom": {
    "name": "Вирівнювання понизу",
    "mediaKey": "76840a92-761c-48f1-b8b4-117664133d04",
    "keys": [
      "аліґн",
      "боттом",
      "вертикаль",
      "вертикальний",
      "вирівнювання",
      "вирівняти",
      "дно",
      "низ",
      "по центру",
      "портрет",
      "стовпчик",
      "align",
      "alignment",
      "bottom",
      "bottom area",
      "footer",
      "layout",
      "portrait",
      "upright",
      "vertical"
    ]
  },
  "vertical-align-center": {
    "name": "Вирівнювання по центру",
    "mediaKey": "5140abb6-91f5-4047-ac14-b3006db8ea26",
    "keys": [
      "аліґн",
      "вертикаль",
      "вертикальний",
      "вирівнювання",
      "вирівняти",
      "кентер",
      "по центру",
      "портрет",
      "стовпчик",
      "центр",
      "центрування",
      "align",
      "alignment",
      "center",
      "center align",
      "layout",
      "middle",
      "portrait",
      "upright",
      "vertical"
    ]
  },
  "vertical-align-top": {
    "name": "Вирівнювання згори",
    "mediaKey": "bdd1aeb1-6469-4582-8335-142ebacff8ef",
    "keys": [
      "аліґн",
      "вертикаль",
      "вертикальний",
      "верх",
      "верхівка",
      "вирівнювання",
      "вирівняти",
      "зверху",
      "лідер",
      "по центру",
      "портрет",
      "стовпчик",
      "топ",
      "align",
      "alignment",
      "layout",
      "max",
      "portrait",
      "top",
      "top list",
      "upright",
      "vertical"
    ]
  },
  "video": {
    "name": "Відео",
    "mediaKey": "47a3615b-310e-4bbb-ad93-bac77621b47f",
    "keys": [
      "відео",
      "відеозапис",
      "кліп",
      "ролик",
      "clip",
      "media",
      "video"
    ]
  },
  "volume-high": {
    "name": "Гучність висока",
    "mediaKey": "47fc1d6c-5644-4a8e-aff9-fe9fe31ebdd4",
    "keys": [
      "верхній",
      "висока",
      "високий",
      "гучність",
      "об'єм",
      "обсяг",
      "повзунок",
      "том",
      "хіґх",
      "altitude",
      "high",
      "high level",
      "loudness",
      "sound level",
      "volume"
    ]
  },
  "volume-low": {
    "name": "Гучність низька",
    "mediaKey": "c8860500-5dcb-496d-8766-1c11e27217c0",
    "keys": [
      "гучність",
      "мінімальний",
      "низька висота",
      "низький",
      "низький рівень",
      "об'єм",
      "обсяг",
      "повзунок",
      "понижений рівень",
      "том",
      "loudness",
      "low",
      "low level",
      "minimum",
      "sound level",
      "volume"
    ]
  },
  "volume-off": {
    "name": "Гучність (вимкнено)",
    "mediaKey": "cb56edee-5ef2-4c7e-9fc3-09f7c6f82dd3",
    "keys": [
      "вимкнено",
      "вимкнути",
      "гучність",
      "об'єм",
      "обсяг",
      "офф",
      "повзунок",
      "том",
      "disabled",
      "loudness",
      "off",
      "off status",
      "sound level",
      "volume"
    ]
  },
  "warning": {
    "name": "Попередження",
    "mediaKey": "817cbda2-268d-4bb9-b185-644f21ad3512",
    "keys": [
      "застереження",
      "попередження",
      "увага",
      "alert",
      "danger",
      "exclamation",
      "warning",
      "warning sign"
    ]
  },
  "wifi": {
    "name": "Сигнал Wi-Fi",
    "mediaKey": "4a886db9-bb91-49ce-9930-f7524a886693",
    "keys": [
      "бездротовий інтернет",
      "вайфай",
      "мережа",
      "hotspot",
      "Wi-Fi",
      "wifi",
      "wireless"
    ]
  },
  "wrench": {
    "name": "Гайковий ключ",
    "mediaKey": "6d350c15-70db-424f-bf64-0a9e0fcb02ab",
    "keys": [
      "гайковий ключ",
      "інструмент",
      "ключ",
      "fix",
      "mechanic",
      "repair",
      "spanner",
      "tool",
      "wrench"
    ]
  },
  "x": {
    "name": "Літера X",
    "mediaKey": "40d91cf9-048c-44dc-8bed-22000bbf9d2d",
    "keys": [
      "ікс",
      "крестик",
      "літера x",
      "невідоме",
      "перехрестя",
      "letter x",
      "x",
      "X",
      "x shape"
    ]
  },
  "yen": {
    "name": "Єна",
    "mediaKey": "a78b2f1c-8898-4f76-a7b3-0d531d318d21",
    "keys": [
      "валюта Японії",
      "гроші",
      "єна",
      "ієна",
      "йена",
      "currency",
      "JPY",
      "yen"
    ]
  },
  "zoom-in": {
    "name": "Збільшення",
    "mediaKey": "47594d12-9517-4571-809e-d1961c5dfd9e",
    "keys": [
      "в",
      "відеодзвінок",
      "всередині",
      "зуми",
      "ін",
      "конференція",
      "in",
      "in icon",
      "input",
      "inside",
      "meeting",
      "video call",
      "zoom",
      "Zoom"
    ]
  },
  "zoom-out": {
    "name": "Зменшити",
    "mediaKey": "a6b671d8-7569-4098-874f-a6f0a7a3faf1",
    "keys": [
      "вийти назовні",
      "відеодзвінок",
      "зовні",
      "зуми",
      "конференція",
      "оут",
      "поза",
      "meeting",
      "out",
      "out state",
      "video call",
      "zoom",
      "Zoom"
    ]
  }
}
