{
  "account": "Обліковий запис",
  "account-box": "Обліковий запис (прямокутник)",
  "alert": "Попередження",
  "alert-box": "Попередження (прямокутник)",
  "alert-box-fill": "Попередження (прямокутник)",
  "alert-circle": "Попередження (коло)",
  "alert-circle-fill": "Попередження (коло)",
  "alert-hexagon": "Попередження (шестикутник)",
  "alert-hexagon-fill": "Попередження (шестикутник)",
  "alert-octagon": "Попередження (восьмикутник)",
  "alert-rhombus": "Попередження (ромб)",
  "alert-rhombus-fill": "Попередження (ромб)",
  "align-horizontal-center": "Горизонтально по центру",
  "align-horizontal-distribute": "Горизонтальний розподіл",
  "align-horizontal-left": "Вирівнювання ліворуч",
  "align-horizontal-right": "Вирівнювання праворуч",
  "align-vertical-bottom": "Вирівнювання по низу",
  "align-vertical-center": "Вертикально по центру",
  "align-vertical-distribute": "Вертикальний розподіл",
  "align-vertical-top": "Вирівнювання по верху",
  "alpha-a": "Літера A",
  "alpha-a-fill": "Літера A",
  "alpha-b": "Літера B",
  "alpha-b-fill": "Літера B",
  "alpha-c": "Літера C",
  "alpha-c-fill": "Літера C",
  "alpha-d": "Літера D",
  "alpha-d-fill": "Літера D",
  "alpha-e": "Літера E",
  "alpha-e-fill": "Літера E",
  "alpha-f": "Літера F",
  "alpha-f-fill": "Літера F",
  "alpha-g": "Літера G",
  "alpha-g-fill": "Літера G",
  "alpha-h": "Літера H",
  "alpha-h-fill": "Літера H",
  "alpha-i": "Літера I",
  "alpha-i-fill": "Літера I",
  "alpha-j": "Літера J",
  "alpha-j-fill": "Літера J",
  "alpha-k": "Літера K",
  "alpha-k-fill": "Літера K",
  "alpha-l": "Літера L",
  "alpha-l-fill": "Літера L",
  "alpha-m": "Літера M",
  "alpha-m-fill": "Літера M",
  "alpha-n": "Літера N",
  "alpha-n-fill": "Літера N",
  "alpha-o": "Літера O",
  "alpha-o-fill": "Літера O",
  "alpha-p": "Літера P",
  "alpha-p-fill": "Літера P",
  "alpha-q": "Літера Q",
  "alpha-q-fill": "Літера Q",
  "alpha-r": "Літера R",
  "alpha-r-fill": "Літера R",
  "alpha-s": "Літера S",
  "alpha-s-fill": "Літера S",
  "alpha-t": "Літера T",
  "alpha-t-fill": "Літера T",
  "alpha-u": "Літера U",
  "alpha-u-fill": "Літера U",
  "alpha-v": "Літера V",
  "alpha-v-fill": "Літера V",
  "alpha-w": "Літера W",
  "alpha-w-fill": "Літера W",
  "alpha-x": "Літера X",
  "alpha-x-fill": "Літера X",
  "alpha-y": "Літера Y",
  "alpha-y-fill": "Літера Y",
  "alpha-z": "Літера Z",
  "alpha-z-fill": "Літера Z",
  "anvil": "Ковадло",
  "application": "Застосунок",
  "application-code": "Код застосунку",
  "apps": "Застосунки",
  "apps-box": "Сітка застосунків",
  "apps-box-fill": "Сітка застосунків",
  "archive": "Архів",
  "arrow": "Стрілка",
  "arrow-bottom-left": "Стрілка вниз ліворуч",
  "arrow-bottom-left-circle": "Стрілка вниз ліворуч у колі",
  "arrow-bottom-right": "Стрілка вниз праворуч",
  "arrow-bottom-right-circle": "Стрілка вниз праворуч у колі",
  "arrow-down": "Стрілка вниз",
  "arrow-down-bold": "Стрілка вниз (жирна)",
  "arrow-down-box": "Стрілка вниз (блок)",
  "arrow-down-circle": "Стрілка вниз (коло)",
  "arrow-down-left": "Стрілка вниз ліворуч",
  "arrow-down-left-box": "Стрілка вниз-ліворуч у прямокутнику",
  "arrow-down-right": "Стрілка вниз праворуч",
  "arrow-down-right-box": "Стрілка вниз-праворуч у прямокутнику",
  "arrow-left": "Стрілка вліво",
  "arrow-left-bold": "Стрілка вліво (жирна)",
  "arrow-left-box": "Стрілка вліво (блок)",
  "arrow-left-circle": "Стрілка вліво (коло)",
  "arrow-left-down": "Стрілка вниз ліворуч",
  "arrow-left-right": "Стрілка двобічна",
  "arrow-left-up": "Стрілка вгору ліворуч",
  "arrow-right": "Стрілка вправо",
  "arrow-right-bold": "Стрілка вправо (жирна)",
  "arrow-right-box": "Стрілка вправо (блок)",
  "arrow-right-circle": "Стрілка вправо (коло)",
  "arrow-right-down": "Стрілка вниз праворуч",
  "arrow-right-up": "Стрілка вгору праворуч",
  "arrow-top-left": "Стрілка вгору ліворуч",
  "arrow-top-left-circle": "Стрілка вгору вліво у колі",
  "arrow-top-right": "Стрілка вгору праворуч",
  "arrow-top-right-circle": "Стрілка вгору вправо у колі",
  "arrow-up": "Стрілка вгору",
  "arrow-up-bold": "Стрілка вгору (жирна)",
  "arrow-up-box": "Стрілка вгору (блок)",
  "arrow-up-circle": "Стрілка вгору (коло)",
  "arrow-up-down": "Стрілки вгору-вниз",
  "arrow-up-left": "Стрілка вгору ліворуч",
  "arrow-up-left-box": "Стрілка вгору-ліворуч у прямокутнику",
  "arrow-up-right": "Стрілка вгору праворуч",
  "arrow-up-right-box": "Стрілка вгору-праворуч у прямокутнику",
  "aspect-ratio": "Співвідношення сторін",
  "axe": "Сокира",
  "bag-personal": "Особиста сумка",
  "bag-personal-fill": "Особиста сумка",
  "bank": "Банк",
  "barcode": "Штрихкод",
  "battery-0": "Акумулятор",
  "battery-100": "Акумулятор",
  "battery-25": "Акумулятор",
  "battery-50": "Акумулятор",
  "battery-75": "Акумулятор",
  "battle-axe": "Battle axe",
  "beer": "Пиво",
  "bell": "Дзвінок",
  "blood": "Кров",
  "book": "Книга",
  "bookmark": "Закладка",
  "border-bottom": "Межа знизу",
  "border-bottom-left": "Рамка знизу зліва",
  "border-bottom-left-right": "Рамка низ + ліво + право",
  "border-bottom-right": "Рамка знизу справа",
  "border-inside": "Внутрішня рамка",
  "border-left": "Межа ліворуч",
  "border-left-right": "Рамка ліворуч і праворуч",
  "border-none": "Без меж",
  "border-outside": "Зовнішня рамка",
  "border-right": "Межа праворуч",
  "border-top": "Межа зверху",
  "border-top-bottom": "Верхня та нижня рамка",
  "border-top-left": "Рамка зверху зліва",
  "border-top-left-bottom": "Рамка зверху зліва + низ",
  "border-top-left-right": "Рамка зверху зліва + право",
  "border-top-right": "Рамка зверху справа",
  "border-top-right-bottom": "Рамка зверху справа + низ",
  "bow": "Лук",
  "bow-arrow": "Лук і стріла",
  "box": "Коробка",
  "box-light-dashed-down-left": "Кут вниз ліворуч (тонка, штрихова)",
  "box-light-dashed-down-right": "Кут вниз праворуч (тонка, штрихова)",
  "box-light-dashed-horizontal": "Горизонтальна (тонка, штрихова)",
  "box-light-dashed-up-left": "Кут вгору ліворуч (тонка, штрихова)",
  "box-light-dashed-up-right": "Кут вгору праворуч (тонка, штрихова)",
  "box-light-dashed-vertical": "Вертикальна (тонка, штрихова)",
  "box-light-dashed-vertical-horizontal": "Перехрестя (тонка, штрихова)",
  "box-light-double-down-left": "Кут вниз ліворуч (тонка, подвійна)",
  "box-light-double-down-right": "Кут вниз праворуч (тонка, подвійна)",
  "box-light-double-horizontal": "Горизонтальна (тонка, подвійна)",
  "box-light-double-horizontal-down": "Т‑перетин вниз (тонка, подвійна)",
  "box-light-double-horizontal-light-down": "Т‑перетин вниз (тонка, подвійна)",
  "box-light-double-horizontal-light-up": "Т‑перетин вгору (тонка, подвійна)",
  "box-light-double-horizontal-up": "Т‑перетин вгору (тонка, подвійна)",
  "box-light-double-round-down-left": "Кут вниз ліворуч (тонка, подвійна, закруглена)",
  "box-light-double-round-down-right": "Кут вниз праворуч (тонка, подвійна, закруглена)",
  "box-light-double-round-up-left": "Кут вгору ліворуч (тонка, подвійна, закруглена)",
  "box-light-double-round-up-right": "Кут вгору праворуч (тонка, подвійна, закруглена)",
  "box-light-double-up-left": "Кут вгору ліворуч (тонка, подвійна)",
  "box-light-double-up-right": "Кут вгору праворуч (тонка, подвійна)",
  "box-light-double-vertical": "Вертикальна (тонка, подвійна)",
  "box-light-double-vertical-horizontal": "Перехрестя (тонка, подвійна)",
  "box-light-double-vertical-left": "Т‑перетин ліворуч (тонка, подвійна)",
  "box-light-double-vertical-light-left": "Т‑перетин ліворуч (тонка, подвійна)",
  "box-light-double-vertical-light-right": "Т‑перетин праворуч (тонка, подвійна)",
  "box-light-double-vertical-right": "Т‑перетин праворуч (тонка, подвійна)",
  "box-light-down-left": "Кут вниз ліворуч (тонка)",
  "box-light-down-left-circle": "Кут вниз ліворуч (кругла, тонка)",
  "box-light-down-left-stipple": "Кут вниз ліворуч (тонка, пунктирна)",
  "box-light-down-left-stipple-inner": "Кут вниз ліворуч (тонка, пунктирна, внутрішня)",
  "box-light-down-left-stipple-outer": "Кут вниз ліворуч (тонка, пунктирна, зовнішня)",
  "box-light-down-right": "Кут вниз праворуч (тонка)",
  "box-light-down-right-circle": "Кут вниз праворуч (кругла, тонка)",
  "box-light-down-right-stipple": "Кут вниз праворуч (тонка, пунктирна)",
  "box-light-down-right-stipple-inner": "Кут вниз праворуч (тонка, пунктирна, внутрішня)",
  "box-light-down-right-stipple-outer": "Кут вниз праворуч (тонка, пунктирна, зовнішня)",
  "box-light-fold-down-left": "Кут вниз ліворуч (тонка)",
  "box-light-fold-down-right": "Кут вниз праворуч (тонка)",
  "box-light-fold-up-left": "Кут вгору ліворуч (тонка)",
  "box-light-fold-up-right": "Кут вгору праворуч (тонка)",
  "box-light-horizontal": "Горизонтальна (тонка)",
  "box-light-horizontal-circle": "Горизонтальна (кругла, тонка)",
  "box-light-horizontal-down": "Т‑перетин вниз (тонка)",
  "box-light-horizontal-down-stipple": "Т‑перетин вниз (тонка, пунктирна)",
  "box-light-horizontal-down-stipple-down": "Т‑перетин вниз (тонка, пунктирна)",
  "box-light-horizontal-down-stipple-down-left": "Кут вниз ліворуч (тонка, пунктирна)",
  "box-light-horizontal-down-stipple-down-right": "Кут вниз праворуч (тонка, пунктирна)",
  "box-light-horizontal-menu-down": "Горизонтальне меню вниз (тонка)",
  "box-light-horizontal-menu-left": "Горизонтальне меню ліворуч (тонка)",
  "box-light-horizontal-menu-right": "Горизонтальне меню праворуч (тонка)",
  "box-light-horizontal-menu-up": "Горизонтальне меню вгору (тонка)",
  "box-light-horizontal-stipple": "Горизонтальна (тонка, пунктирна)",
  "box-light-horizontal-stipple-down": "Т‑перетин вниз (тонка, пунктирна)",
  "box-light-horizontal-stipple-up": "Т‑перетин вгору (тонка, пунктирна)",
  "box-light-horizontal-up": "Т‑перетин вгору (тонка)",
  "box-light-horizontal-up-stipple": "Т‑перетин вгору (тонка, пунктирна)",
  "box-light-horizontal-up-stipple-down": "Т‑перетин вгору-вниз (тонка, пунктирна)",
  "box-light-horizontal-up-stipple-up": "Т‑перетин вгору (тонка, пунктирна)",
  "box-light-horizontal-up-stipple-up-left": "Кут вгору ліворуч (тонка, пунктирна)",
  "box-light-horizontal-up-stipple-up-right": "Кут вгору праворуч (тонка, пунктирна)",
  "box-light-round-down-left": "Кут вниз ліворуч (тонка, закруглена)",
  "box-light-round-down-left-stipple": "Кут вниз ліворуч (тонка, закруглена, пунктирна)",
  "box-light-round-down-left-stipple-inner": "Кут вниз ліворуч (тонка, закруглена, пунктирна, внутрішня)",
  "box-light-round-down-left-stipple-outer": "Кут вниз ліворуч (тонка, закруглена, пунктирна, зовнішня)",
  "box-light-round-down-right": "Кут вниз праворуч (тонка, закруглена)",
  "box-light-round-down-right-stipple": "Кут вниз праворуч (тонка, закруглена, пунктирна)",
  "box-light-round-down-right-stipple-inner": "Кут вниз праворуч (тонка, закруглена, пунктирна, внутрішня)",
  "box-light-round-down-right-stipple-outer": "Кут вниз праворуч (тонка, закруглена, пунктирна, зовнішня)",
  "box-light-round-up-left": "Кут вгору ліворуч (тонка, закруглена)",
  "box-light-round-up-left-stipple": "Кут вгору ліворуч (тонка, закруглена, пунктирна)",
  "box-light-round-up-left-stipple-inner": "Кут вгору ліворуч (тонка, закруглена, пунктирна, внутрішня)",
  "box-light-round-up-left-stipple-outer": "Кут вгору ліворуч (тонка, закруглена, пунктирна, зовнішня)",
  "box-light-round-up-right": "Кут вгору праворуч (тонка, закруглена)",
  "box-light-round-up-right-stipple": "Кут вгору праворуч (тонка, закруглена, пунктирна)",
  "box-light-round-up-right-stipple-inner": "Кут вгору праворуч (тонка, закруглена, пунктирна, внутрішня)",
  "box-light-round-up-right-stipple-outer": "Кут вгору праворуч (тонка, закруглена, пунктирна, зовнішня)",
  "box-light-up-left": "Кут вгору ліворуч (тонка)",
  "box-light-up-left-circle": "Кут вгору ліворуч (кругла, тонка)",
  "box-light-up-left-stipple": "Кут вгору ліворуч (тонка, пунктирна)",
  "box-light-up-left-stipple-inner": "Кут вгору ліворуч (тонка, пунктирна, внутрішня)",
  "box-light-up-left-stipple-outer": "Кут вгору ліворуч (тонка, пунктирна, зовнішня)",
  "box-light-up-right": "Кут вгору праворуч (тонка)",
  "box-light-up-right-circle": "Кут вгору праворуч (кругла, тонка)",
  "box-light-up-right-stipple": "Кут вгору праворуч (тонка, пунктирна)",
  "box-light-up-right-stipple-inner": "Кут вгору праворуч (тонка, пунктирна, внутрішня)",
  "box-light-up-right-stipple-outer": "Кут вгору праворуч (тонка, пунктирна, зовнішня)",
  "box-light-vertical": "Вертикальна (тонка)",
  "box-light-vertical-circle": "Вертикальна (кругла, тонка)",
  "box-light-vertical-horizontal": "Перехрестя (тонка)",
  "box-light-vertical-horizontal-stipple": "Перехрестя (тонка, пунктирна)",
  "box-light-vertical-horizontal-stipple-down": "Перехрестя вниз (тонка, пунктирна)",
  "box-light-vertical-horizontal-stipple-down-left": "Перехрестя вниз ліворуч (тонка, пунктирна)",
  "box-light-vertical-horizontal-stipple-down-right": "Перехрестя вниз праворуч (тонка, пунктирна)",
  "box-light-vertical-horizontal-stipple-left": "Перехрестя ліворуч (тонка, пунктирна)",
  "box-light-vertical-horizontal-stipple-left-down-right": "Перехрестя ліворуч вниз праворуч (тонка, пунктирна)",
  "box-light-vertical-horizontal-stipple-left-up-right": "Перехрестя ліворуч вгору праворуч (тонка, пунктирна)",
  "box-light-vertical-horizontal-stipple-right": "Перехрестя праворуч (тонка, пунктирна)",
  "box-light-vertical-horizontal-stipple-right-down-left": "Перехрестя праворуч вниз ліворуч (тонка, пунктирна)",
  "box-light-vertical-horizontal-stipple-right-up-left": "Перехрестя праворуч вгору ліворуч (тонка, пунктирна)",
  "box-light-vertical-horizontal-stipple-up": "Перехрестя вгору (тонка, пунктирна)",
  "box-light-vertical-horizontal-stipple-up-left": "Перехрестя вгору ліворуч (тонка, пунктирна)",
  "box-light-vertical-horizontal-stipple-up-right": "Перехрестя вгору праворуч (тонка, пунктирна)",
  "box-light-vertical-left": "Т‑перетин ліворуч (тонка)",
  "box-light-vertical-left-stipple": "Т‑перетин ліворуч (тонка, пунктирна)",
  "box-light-vertical-left-stipple-down-left": "Кут вниз ліворуч (тонка, пунктирна)",
  "box-light-vertical-left-stipple-left": "Т‑перетин ліворуч (тонка, пунктирна)",
  "box-light-vertical-left-stipple-up-left": "Кут вгору ліворуч (тонка, пунктирна)",
  "box-light-vertical-menu-down": "Вертикальне меню вниз (тонка)",
  "box-light-vertical-menu-left": "Вертикальне меню ліворуч (тонка)",
  "box-light-vertical-menu-right": "Вертикальне меню праворуч (тонка)",
  "box-light-vertical-menu-up": "Вертикальне меню вгору (тонка)",
  "box-light-vertical-right": "Т‑перетин праворуч (тонка)",
  "box-light-vertical-right-stipple": "Т‑перетин праворуч (тонка, пунктирна)",
  "box-light-vertical-right-stipple-down-right": "Кут вниз праворуч (тонка, пунктирна)",
  "box-light-vertical-right-stipple-left": "Т‑перетин праворуч ліворуч (тонка, пунктирна)",
  "box-light-vertical-right-stipple-right": "Т‑перетин праворуч (тонка, пунктирна)",
  "box-light-vertical-right-stipple-up-right": "Кут вгору праворуч (тонка, пунктирна)",
  "box-light-vertical-stipple": "Вертикальна (тонка, пунктирна)",
  "box-light-vertical-stipple-left": "Т‑перетин ліворуч (тонка, пунктирна)",
  "box-light-vertical-stipple-right": "Т‑перетин праворуч (тонка, пунктирна)",
  "box-outer-light-all": "Елемент рамки (зовнішня, тонка)",
  "box-outer-light-dashed-all": "Елемент рамки (зовнішня, тонка, штрихова)",
  "box-outer-light-dashed-down": "Елемент рамки вниз (зовнішня, тонка, штрихова)",
  "box-outer-light-dashed-down-left": "Кут вниз ліворуч (зовнішня, тонка, штрихова)",
  "box-outer-light-dashed-down-left-right": "Кут вниз ліворуч (зовнішня, тонка, штрихова)",
  "box-outer-light-dashed-down-right": "Кут вниз праворуч (зовнішня, тонка, штрихова)",
  "box-outer-light-dashed-fold-down-left": "Кут вниз ліворуч (зовнішня, тонка, штрихова)",
  "box-outer-light-dashed-fold-down-right": "Кут вниз праворуч (зовнішня, тонка, штрихова)",
  "box-outer-light-dashed-fold-up-left": "Кут вгору ліворуч (зовнішня, тонка, штрихова)",
  "box-outer-light-dashed-fold-up-right": "Кут вгору праворуч (зовнішня, тонка, штрихова)",
  "box-outer-light-dashed-left": "Елемент рамки ліворуч (зовнішня, тонка, штрихова)",
  "box-outer-light-dashed-left-right": "Елемент рамки ліворуч праворуч (зовнішня, тонка, штрихова)",
  "box-outer-light-dashed-right": "Елемент рамки праворуч (зовнішня, тонка, штрихова)",
  "box-outer-light-dashed-up": "Елемент рамки вгору (зовнішня, тонка, штрихова)",
  "box-outer-light-dashed-up-down": "Елемент рамки вгору-вниз (зовнішня, тонка, штрихова)",
  "box-outer-light-dashed-up-down-left": "Кут вгору ліворуч (зовнішня, тонка, штрихова)",
  "box-outer-light-dashed-up-down-right": "Кут вгору праворуч (зовнішня, тонка, штрихова)",
  "box-outer-light-dashed-up-left": "Кут вгору ліворуч (зовнішня, тонка, штрихова)",
  "box-outer-light-dashed-up-left-right": "Кут вгору ліворуч (зовнішня, тонка, штрихова)",
  "box-outer-light-dashed-up-right": "Кут вгору праворуч (зовнішня, тонка, штрихова)",
  "box-outer-light-down": "Елемент рамки вниз (зовнішня, тонка)",
  "box-outer-light-down-left": "Кут вниз ліворуч (зовнішня, тонка)",
  "box-outer-light-down-left-right": "Кут вниз ліворуч (зовнішня, тонка)",
  "box-outer-light-down-left-stipple": "Кут вниз ліворуч (зовнішня, тонка, пунктирна)",
  "box-outer-light-down-right": "Кут вниз праворуч (зовнішня, тонка)",
  "box-outer-light-down-right-stipple": "Кут вниз праворуч (зовнішня, тонка, пунктирна)",
  "box-outer-light-down-stipple": "Елемент рамки вниз (зовнішня, тонка, пунктирна)",
  "box-outer-light-down-vertical-stipple": "Вертикальна (зовнішня, тонка, пунктирна)",
  "box-outer-light-down-vertical-stipple-left": "Кут вниз ліворуч (зовнішня, тонка, пунктирна)",
  "box-outer-light-down-vertical-stipple-right": "Кут вниз праворуч (зовнішня, тонка, пунктирна)",
  "box-outer-light-left": "Елемент рамки ліворуч (зовнішня, тонка)",
  "box-outer-light-left-horizontal-stipple": "Горизонтальна (зовнішня, тонка, пунктирна)",
  "box-outer-light-left-horizontal-stipple-down": "Кут вниз ліворуч (зовнішня, тонка, пунктирна)",
  "box-outer-light-left-horizontal-stipple-up": "Кут вгору ліворуч (зовнішня, тонка, пунктирна)",
  "box-outer-light-left-right": "Елемент рамки ліворуч праворуч (зовнішня, тонка)",
  "box-outer-light-left-right-stipple": "Елемент рамки ліворуч праворуч (зовнішня, тонка, пунктирна)",
  "box-outer-light-left-stipple": "Елемент рамки ліворуч (зовнішня, тонка, пунктирна)",
  "box-outer-light-right": "Елемент рамки праворуч (зовнішня, тонка)",
  "box-outer-light-right-horizontal-stipple": "Горизонтальна (зовнішня, тонка, пунктирна)",
  "box-outer-light-right-horizontal-stipple-down": "Кут вниз праворуч (зовнішня, тонка, пунктирна)",
  "box-outer-light-right-horizontal-stipple-up": "Кут вгору праворуч (зовнішня, тонка, пунктирна)",
  "box-outer-light-right-stipple": "Елемент рамки праворуч (зовнішня, тонка, пунктирна)",
  "box-outer-light-round-down-left": "Кут вниз ліворуч (зовнішня, тонка, закруглена)",
  "box-outer-light-round-down-right": "Кут вниз праворуч (зовнішня, тонка, закруглена)",
  "box-outer-light-round-up-left": "Кут вгору ліворуч (зовнішня, тонка, закруглена)",
  "box-outer-light-round-up-right": "Кут вгору праворуч (зовнішня, тонка, закруглена)",
  "box-outer-light-up": "Елемент рамки вгору (зовнішня, тонка)",
  "box-outer-light-up-down": "Елемент рамки вгору-вниз (зовнішня, тонка)",
  "box-outer-light-up-down-left": "Кут вгору ліворуч (зовнішня, тонка)",
  "box-outer-light-up-down-right": "Кут вгору праворуч (зовнішня, тонка)",
  "box-outer-light-up-down-stipple": "Елемент рамки вгору-вниз (зовнішня, тонка, пунктирна)",
  "box-outer-light-up-left": "Кут вгору ліворуч (зовнішня, тонка)",
  "box-outer-light-up-left-right": "Кут вгору ліворуч (зовнішня, тонка)",
  "box-outer-light-up-left-stipple": "Кут вгору ліворуч (зовнішня, тонка, пунктирна)",
  "box-outer-light-up-right": "Кут вгору праворуч (зовнішня, тонка)",
  "box-outer-light-up-right-stipple": "Кут вгору праворуч (зовнішня, тонка, пунктирна)",
  "box-outer-light-up-stipple": "Елемент рамки вгору (зовнішня, тонка, пунктирна)",
  "box-outer-light-up-vertical-stipple": "Вертикальна (зовнішня, тонка, пунктирна)",
  "box-outer-light-up-vertical-stipple-left": "Кут вгору ліворуч (зовнішня, тонка, пунктирна)",
  "box-outer-light-up-vertical-stipple-right": "Кут вгору праворуч (зовнішня, тонка, пунктирна)",
  "briefcase": "Портфель",
  "broadcast": "Трансляція",
  "bug": "Жук",
  "bug-fill": "Жук",
  "calculator": "Калькулятор",
  "calendar": "Календар",
  "calendar-import": "Календар (імпорт)",
  "calendar-month": "Календар (місяць)",
  "cancel": "Скасування",
  "card": "Картка",
  "card-text": "Текст картки",
  "cart": "Кошик",
  "cash": "Готівка",
  "cast": "Трансляція",
  "castle": "Замок",
  "chart-bar": "Діаграма (стовпці)",
  "chat": "Чат",
  "chat-processing": "Обробка чату",
  "check": "Галочка",
  "checkbox-blank": "Порожній чекбокс",
  "checkbox-cross": "Checkbox хрест",
  "checkbox-intermediate": "Проміжний чекбокс",
  "checkbox-intermediate-variant": "Проміжний чекбокс (варіант)",
  "checkbox-marked": "Позначений чекбокс",
  "checker-large": "Шашка (велика)",
  "checker-medium": "Checker середній",
  "checker-small": "Шашка (мала)",
  "checkerboard": "Шахова дошка",
  "chest": "Скриня",
  "chest-fill": "Скриня",
  "chevron-down": "Шеврон вниз",
  "chevron-down-circle": "Шеврон вниз (коло)",
  "chevron-left": "Шеврон ліворуч",
  "chevron-left-circle": "Шеврон ліворуч (коло)",
  "chevron-right": "Шеврон праворуч",
  "chevron-right-circle": "Шеврон праворуч (коло)",
  "chevron-up": "Шеврон вгору",
  "chevron-up-circle": "Шеврон вгору (коло)",
  "circle": "Коло",
  "clipboard": "Буфер обміну",
  "clock": "Годинник",
  "clock-fill": "Годинник (заповнена)",
  "close": "Закрити",
  "close-outline": "Закрити",
  "cloud": "Хмара",
  "cloud-down": "Хмара (стрілка вниз)",
  "cloud-up": "Хмара (стрілка вгору)",
  "coffee": "Кава",
  "coin-copper": "Монета copper",
  "coin-electrum": "Монета electrum",
  "coin-gold": "Монета gold",
  "coin-platinum": "Монета platinum",
  "coin-silver": "Монета silver",
  "comment": "Коментар",
  "comment-text": "Текст коментаря",
  "comment-user": "Comment користувач",
  "compass": "Компас",
  "compass-east-arrow": "Компас east стрілка",
  "compass-north-arrow": "Компас north стрілка",
  "compass-north-east": "Компас north east",
  "compass-north-west": "Компас north west",
  "compass-south-arrow": "Компас south стрілка",
  "compass-south-east": "Компас south east",
  "compass-south-west": "Компас south west",
  "compass-west-arrow": "Компас west стрілка",
  "credit-card": "Кредитна картка",
  "crossbow": "Арбалет",
  "crown": "Корона",
  "cube": "Куб",
  "cube-unfolded": "Розгорнутий куб",
  "dagger": "Кинджал",
  "database": "База даних",
  "device": "Пристрій",
  "diamond": "Діамант",
  "division": "Ділення",
  "door": "Двері",
  "door-box": "Двері (коробка)",
  "door-open": "Відчинені двері",
  "dot-hexagon": "Крапка (шестикутна)",
  "dot-hexagon-fill": "Крапка (шестикутна)",
  "dot-octagon": "Крапка (восьмикутна)",
  "dot-octagon-fill": "Крапка (восьмикутна)",
  "download": "Завантажити",
  "email": "Пошта",
  "eye": "Око",
  "eye-fill": "Око (заливка)",
  "file": "Файл",
  "fill": "Заливка",
  "filter": "Фільтр",
  "fire": "Вогонь",
  "flask": "Колба",
  "flask-empty": "Порожня колба",
  "flask-round-bottom": "Колба з круглим дном",
  "flask-round-bottom-empty": "Порожня колба з круглим дном",
  "floppy-disk": "Дискета",
  "folder": "Папка",
  "folder-open": "Папка (відкрита)",
  "format-align-bottom": "Вирівняти донизу",
  "format-align-center": "Вирівняти по центру",
  "format-align-justify": "Вирівняти за шириною",
  "format-align-left": "Вирівняти ліворуч",
  "format-align-right": "Вирівняти праворуч",
  "format-align-top": "Вирівняти догори",
  "format-bold": "Формат жирний",
  "format-float-left": "Обтікання ліворуч",
  "format-float-right": "Обтікання праворуч",
  "format-horizontal-align-center": "Горизонтальне вирівнювання по центру",
  "format-italic": "Формат курсив",
  "format-line-spacing": "Міжрядковий відступ",
  "format-text": "Текстове форматування",
  "format-text-multiline": "Формат тексту (кілька рядків)",
  "format-text-single-line": "Format text single line (контурна)",
  "format-vertical-align-center": "Вертикальне вирівнювання по центру",
  "gamepad": "Геймпад",
  "gamepad-center": "Геймпад (центр)",
  "gamepad-center-fill": "Геймпад (центр)",
  "gamepad-down": "Геймпад вниз",
  "gamepad-down-fill": "Геймпад вниз",
  "gamepad-down-left": "Геймпад (вниз-ліворуч)",
  "gamepad-down-left-fill": "Геймпад (вниз-ліворуч)",
  "gamepad-down-right": "Геймпад (вниз-праворуч)",
  "gamepad-down-right-fill": "Геймпад (вниз-праворуч)",
  "gamepad-fill": "Геймпад",
  "gamepad-left": "Геймпад вліво",
  "gamepad-left-fill": "Геймпад вліво",
  "gamepad-right": "Геймпад вправо",
  "gamepad-right-fill": "Геймпад вправо",
  "gamepad-up": "Геймпад вгору",
  "gamepad-up-fill": "Геймпад вгору",
  "gamepad-up-left": "Геймпад (вгору-ліворуч)",
  "gamepad-up-left-fill": "Геймпад (вгору-ліворуч)",
  "gamepad-up-right": "Геймпад (вгору-праворуч)",
  "gamepad-up-right-fill": "Геймпад (вгору-праворуч)",
  "glaive": "Глефа",
  "glasses": "Окуляри",
  "halberd": "Алебарда",
  "heart": "Серце",
  "heart-broken": "Розбите серце",
  "help": "Допомога",
  "help-box": "Довідка (квадрат)",
  "help-box-fill": "Довідка (квадрат)",
  "hexagon": "Шестикутник",
  "home-thatched": "Хата",
  "image": "Зображення",
  "javalin": "Javalin",
  "journal": "Журнал",
  "key": "Ключ",
  "label": "Мітка",
  "label-variant": "Мітка (варіант)",
  "lance": "Lance",
  "led": "LED",
  "lightbulb": "Лампочка",
  "linen": "Linen",
  "lock": "Замок",
  "lock-open": "Замок (відкритий)",
  "login": "Логін",
  "logout": "Вихід",
  "magnify-minus": "Лупа мінус",
  "magnify-plus": "Лупа плюс",
  "map": "Карта",
  "menu-bottom-left": "Меню (знизу ліворуч)",
  "menu-bottom-right": "Меню (знизу праворуч)",
  "menu-down": "Меню вниз",
  "menu-down-fill": "Меню вниз",
  "menu-left": "Меню вліво",
  "menu-left-fill": "Меню вліво",
  "menu-left-right": "Меню — ліворуч/праворуч",
  "menu-right": "Меню вправо",
  "menu-right-fill": "Меню вправо",
  "menu-top-left": "Меню (згори ліворуч)",
  "menu-top-right": "Меню (згори праворуч)",
  "menu-up": "Меню вгору",
  "menu-up-down": "Меню — вгору/вниз",
  "menu-up-fill": "Меню вгору",
  "message": "Повідомлення",
  "message-processing": "Повідомлення (обробка)",
  "message-text": "Повідомлення з текстом",
  "message-user": "Повідомлення (користувач)",
  "microphone": "Мікрофон",
  "minus": "Мінус",
  "minus-box": "Мінус у квадраті",
  "minus-box-fill": "Мінус у квадраті",
  "minus-circle": "Мінус у колі",
  "minus-circle-fill": "Мінус у колі",
  "monitor": "Монітор",
  "monitor-image": "Монітор із зображенням",
  "multiply": "Множення",
  "music-note": "Нота",
  "necklace": "Намисто",
  "note": "Примітка",
  "note-nailed": "Нотатка прибита",
  "notebook": "Блокнот",
  "notification": "Сповіщення",
  "number": "Число",
  "octagon": "Восьмикутник",
  "paperclip": "Скріпка",
  "pause": "Пауза",
  "peace": "Мир",
  "pencil": "Олівець",
  "pickaxe": "Кайло",
  "pictogrammers": "Pictogrammers",
  "pike": "Pike",
  "play": "Грати",
  "plus": "Плюс",
  "plus-box": "Плюс у блоці",
  "plus-box-fill": "Плюс у блоці",
  "plus-circle": "Плюс у колі",
  "plus-circle-fill": "Плюс у колі (заливка)",
  "poll": "Опитування",
  "pound": "Фунт",
  "quarterstaff": "Quarterstaff",
  "radiobox": "Radiobox",
  "radiobox-marked": "Позначена радіокнопка",
  "range": "Range",
  "relative-scale": "Відносна шкала",
  "remove-circle": "Видалити (коло)",
  "ring": "Каблучка",
  "rotate-clockwise": "Поворот за годинниковою стрілкою",
  "rotate-counterclockwise": "Повернути проти годинникової",
  "scimitar": "Scimitar",
  "script": "Скрипт",
  "search": "Пошук",
  "shield": "Щит",
  "shovel": "Лопата",
  "skull": "Череп",
  "slider-end": "Кінець повзунка",
  "slider-right": "Slider Вправо",
  "speaker": "Динамік",
  "spear": "Спис",
  "stool": "Табурет",
  "stop": "Зупинити",
  "sword": "Меч",
  "table-top-door-horizontal": "План зверху (горизонтальна)",
  "table-top-door-one-way-down": "План зверху",
  "table-top-door-one-way-left": "План зверху",
  "table-top-door-one-way-right": "План зверху",
  "table-top-door-one-way-up": "План зверху",
  "table-top-door-secret-horizontal": "План зверху (горизонтальна)",
  "table-top-door-secret-vertical": "План зверху (вертикальна)",
  "table-top-door-vertical": "План зверху (вертикальна)",
  "table-top-horizontal-rotate-clockwise": "План зверху (горизонтальна)",
  "table-top-horizontal-rotate-counterclockwise": "План зверху (горизонтальна)",
  "table-top-horizontal-stairs-ascend-left": "План зверху (горизонтальна)",
  "table-top-horizontal-stairs-ascend-right": "План зверху (горизонтальна)",
  "table-top-horizontal-stairs-descend-down": "План зверху (горизонтальна)",
  "table-top-horizontal-stairs-descend-left": "План зверху (горизонтальна)",
  "table-top-horizontal-stairs-descend-right": "План зверху (горизонтальна)",
  "table-top-horizontal-stairs-descend-up": "План зверху (горизонтальна)",
  "table-top-spiral-stairs-down": "План зверху",
  "table-top-spiral-stairs-left": "План зверху",
  "table-top-spiral-stairs-right": "План зверху",
  "table-top-spiral-stairs-round-down": "План зверху",
  "table-top-spiral-stairs-round-left": "План зверху",
  "table-top-spiral-stairs-round-right": "План зверху",
  "table-top-spiral-stairs-round-up": "План зверху",
  "table-top-spiral-stairs-up": "План зверху",
  "table-top-stairs-down": "План зверху",
  "table-top-stairs-left": "План зверху",
  "table-top-stairs-right": "План зверху",
  "table-top-stairs-up": "План зверху",
  "table-top-vertical-rotate-clockwise": "План зверху (вертикальна)",
  "table-top-vertical-rotate-counterclockwise": "План зверху (вертикальна)",
  "table-top-vertical-stairs-ascend-down": "План зверху (вертикальна)",
  "table-top-vertical-stairs-ascend-up": "План зверху (вертикальна)",
  "tag": "Тег",
  "tag-text": "Текстовий тег",
  "target": "Мішень",
  "tent": "Намет",
  "terminal": "Термінал",
  "text-box": "Текстове поле",
  "text-image": "Текст і зображення",
  "tile-caution-heavy": "Плитка попередження",
  "tile-caution-thin": "Tile (тонка)",
  "tile-diamond-hex": "Tile (ромбова)",
  "time-sand": "Пісочний годинник",
  "toggle-switch-off": "Перемикач вимкнено",
  "toggle-switch-on": "Перемикач увімкнено",
  "toolbox": "Ящик з інструментами",
  "tooltip-above": "Підказка",
  "tooltip-above-alert": "Підказка",
  "tooltip-above-help": "Підказка",
  "tooltip-above-text": "Підказка",
  "tooltip-below": "Підказка",
  "tooltip-below-alert": "Підказка",
  "tooltip-below-help": "Підказка",
  "tooltip-below-text": "Підказка",
  "tooltip-end": "Підказка",
  "tooltip-end-alert": "Підказка",
  "tooltip-end-help": "Підказка",
  "tooltip-end-text": "Підказка",
  "tooltip-start": "Підказка",
  "tooltip-start-alert": "Підказка",
  "tooltip-start-help": "Підказка",
  "tooltip-start-text": "Підказка",
  "torch": "Ліхтар",
  "toy-brick": "Іграшковий кубик",
  "trash": "Сміття",
  "trident": "Тризуб",
  "umbrella": "Парасолька",
  "upload": "Завантажити",
  "volume-high": "Гучність висока",
  "volume-low": "Гучність низька",
  "volume-medium": "Гучність середня",
  "volume-mute": "Гучність вимкнено",
  "wall": "Стіна",
  "wall-fill": "Стіна",
  "wall-front": "Стіна спереду",
  "wall-front-damaged": "Стіна спереду (пошкоджена)",
  "wall-front-gate": "Стіна спереду (ворота)",
  "water": "Вода",
  "water-fill": "Вода",
  "weight": "Вага",
  "weight-fill": "Вага",
  "well": "Well",
  "whip": "Батіг",
  "wind": "Вітер"
}
