{
  "slug": "abstract-geometric-shapes-with-gradient-colors-on-black-background-9kfpiihczni",
  "name": "Abstract geometric composition with orange circles and pink gradient shapes",
  "category": "Зображення",
  "source": "https://unsplash.com/illustrations/abstract-geometric-shapes-with-gradient-colors-on-black-background-9kfPIIHCZNI",
  "authorName": "Pixeliota",
  "authorUrl": "https://unsplash.com/@pixeliota",
  "description": "Abstract geometric composition with orange circles and pink gradient shapes",
  "keys": [
    "abstract",
    "art",
    "gradient",
    "pink",
    "illustration",
    "design",
    "orange",
    "graphic design",
    "abstract art",
    "vector",
    "graphic",
    "modern art",
    "circle",
    "digital art",
    "geometric pattern",
    "modern",
    "geometric"
  ],
  "tags": [
    "абстракція",
    "мистецтво",
    "градієнт",
    "рожевий",
    "illustration",
    "дизайн",
    "помаранчевий",
    "графічний дизайн",
    "абстрактне мистецтво",
    "vector",
    "graphic",
    "сучасне мистецтво",
    "circle",
    "цифрове мистецтво",
    "geometric pattern",
    "сучасний",
    "геометричний"
  ],
  "licenseName": "Unsplash License",
  "licenseUrl": "https://unsplash.com/license",
  "tier": "plus",
  "downloadSource": "api"
}
