{
  "slug": "a-computer-generated-image-of-a-group-of-people-qq8oigiseze",
  "name": "Ретро-футуристична ілюстрація",
  "category": "Ілюстрації",
  "source": "https://unsplash.com/illustrations/a-computer-generated-image-of-a-group-of-people-qq8OIgiSeZE",
  "authorName": "Ardian Pranomo",
  "authorUrl": "https://unsplash.com/@ardianpranomo",
  "keys": [
    "80s aesthetic",
    "градієнтний фон",
    "gradient background",
    "gradients",
    "illustration",
    "retro futuristic",
    "retro neon",
    "vector"
  ],
  "tags": [
    "ілюстрація",
    "векторний",
    "градієнт",
    "ретро-футуристичний",
    "ретро-неон",
    "естетика 80-х"
  ],
  "licenseName": "Unsplash License",
  "licenseUrl": "https://unsplash.com/license",
  "tier": "plus",
  "downloadSource": "downloads",
  "sourceName": "Unsplash"
}
